Workbook
Name Scenario: Levers!$C$4
Name SmallerModel: Levers!$C$7
Name FewerTokens: Levers!$C$8
Name TrainSpeed: Levers!$C$9
Name MemoryLever: Levers!$C$10
Name ServeThroughput: Levers!$C$11
Name TrainLever: Levers!$C$14
Name ServeComputeLever: Levers!$C$16
Name ServeGPULever: Levers!$C$17

Sheet Summary
A1: HELARCTOS × AI CAPEX — what a more efficient AI architecture is worth
A2: ="In FY2026 the six largest AI spenders (Microsoft, Alphabet, Amazon, Meta, Oracle, SpaceX) will spend ~$"&TEXT('Value Bridge'!M70,"#,##0")&"B on AI and earn ~$"&TEXT('Value Bridge'!O70,"#,##0")&"B from it. Helarctos models do the same AI work — training and inference at the same quality — on a fraction of the hardware. This page shows how much of that spend becomes unnecessary, and where the savings come from."
A3: ="Scenario: "&Scenario&" (change it on the Levers tab)"
A5: THE HEADLINE | B5: FY2026 (now) | C5: FY2025
A6: AI spend: chips, data centres, power | B6: ='Value Bridge'!M70 | C6: ='Value Bridge'!M81
A7: AI revenue | B7: ='Value Bridge'!O70 | C7: ='Value Bridge'!O81
A8: Net AI cash result today | B8: ='Value Bridge'!P70 | C8: ='Value Bridge'!P81
A9: Spend Helarctos makes unnecessary, per year | B9: ='Value Bridge'!L70 | C9: ='Value Bridge'!L81
A10: …as a share of AI spend | B10: ='Value Bridge'!N70 | C10: ='Value Bridge'!N81
A11: Net AI cash result with Helarctos | B11: ='Value Bridge'!Q70 | C11: ='Value Bridge'!Q81
A12: Value of that saving, capitalized at the discount rate | B12: ='Value Bridge'!L70/Inputs!$B$6/1000 | C12: ='Value Bridge'!L81/Inputs!$B$6/1000
A14: WHERE THE SAVINGS COME FROM — FY2026, $B per year
A15: Where | B15: $B / yr (capex + power) | C15: share | D15: How Helarctos does it
A16: Training | B16: ='Value Bridge'!F70+'Value Bridge'!J70 | C16: =B16/$B$18 | D16: ="Same-quality model is "&TEXT(SmallerModel,"0.0")&"× smaller and needs "&TEXT(FewerTokens,"0.0")&"× fewer training tokens (training speed per token is about the same) → "&TEXT(TrainLever,"0")&"× fewer GPU-hours → smaller training clusters, and the power they would draw."
A17: Inference | B17: ='Value Bridge'!G70+'Value Bridge'!K70 | C17: =B17/$B$18 | D17: ="A transformer's memory grows with every token of every live conversation; Helarctos keeps a fixed-size state (÷"&TEXT(MemoryLever,"0")&" memory) and does "&TEXT(ServeComputeLever,"0")&"× less compute per token. A GPU is bought whole, so the fleet shrinks by whichever limit binds: "&TEXT(ServeGPULever,"0")&"× fewer inference GPUs, and their power."
A18: TOTAL | B18: =SUM(B16:B17) | C18: =SUM(C16:C17)
A19: Step-by-step build and the one-lever-at-a-time view: Value Bridge tab.
A23: BY COMPANY — FY2026, $B
A24: Company | B24: AI spend | C24: Training saving | D24: Inference saving | E24: Helarctos saving / yr | F24: % of AI spend | G24: Net AI today | H24: Net AI with Helarctos
A25: Microsoft | B25: ='Value Bridge'!M64 | C25: ='Value Bridge'!F64+'Value Bridge'!J64 | D25: ='Value Bridge'!G64+'Value Bridge'!K64 | E25: ='Value Bridge'!L64 | F25: ='Value Bridge'!N64 | G25: ='Value Bridge'!P64 | H25: ='Value Bridge'!Q64
A26: Alphabet | B26: ='Value Bridge'!M65 | C26: ='Value Bridge'!F65+'Value Bridge'!J65 | D26: ='Value Bridge'!G65+'Value Bridge'!K65 | E26: ='Value Bridge'!L65 | F26: ='Value Bridge'!N65 | G26: ='Value Bridge'!P65 | H26: ='Value Bridge'!Q65
A27: Amazon | B27: ='Value Bridge'!M66 | C27: ='Value Bridge'!F66+'Value Bridge'!J66 | D27: ='Value Bridge'!G66+'Value Bridge'!K66 | E27: ='Value Bridge'!L66 | F27: ='Value Bridge'!N66 | G27: ='Value Bridge'!P66 | H27: ='Value Bridge'!Q66
A28: Meta | B28: ='Value Bridge'!M67 | C28: ='Value Bridge'!F67+'Value Bridge'!J67 | D28: ='Value Bridge'!G67+'Value Bridge'!K67 | E28: ='Value Bridge'!L67 | F28: ='Value Bridge'!N67 | G28: ='Value Bridge'!P67 | H28: ='Value Bridge'!Q67
A29: Oracle | B29: ='Value Bridge'!M68 | C29: ='Value Bridge'!F68+'Value Bridge'!J68 | D29: ='Value Bridge'!G68+'Value Bridge'!K68 | E29: ='Value Bridge'!L68 | F29: ='Value Bridge'!N68 | G29: ='Value Bridge'!P68 | H29: ='Value Bridge'!Q68
A30: SpaceX | B30: ='Value Bridge'!M69 | C30: ='Value Bridge'!F69+'Value Bridge'!J69 | D30: ='Value Bridge'!G69+'Value Bridge'!K69 | E30: ='Value Bridge'!L69 | F30: ='Value Bridge'!N69 | G30: ='Value Bridge'!P69 | H30: ='Value Bridge'!Q69
A31: TOTAL (6) | B31: ='Value Bridge'!M70 | C31: ='Value Bridge'!F70+'Value Bridge'!J70 | D31: ='Value Bridge'!G70+'Value Bridge'!K70 | E31: ='Value Bridge'!L70 | F31: ='Value Bridge'!N70 | G31: ='Value Bridge'!P70 | H31: ='Value Bridge'!Q70
A33: WHY THE ANSWER IS ~99% OF THE CHIP BILL — NOT "1,000×"
A34: Multiples don't multiply. A GPU is bought whole — memory and compute together — so an inference fleet shrinks by whichever need falls LEAST (here the conservative 100× memory cap), not by 100 × 793. Cutting a fleet 100× already removes 99% of it; bigger multiples can only move the last 1%. So the dollars are set by how much these firms spend on chips, not by how large the multiple is. We report dollars.
A36: HOW TO READ THIS WORKBOOK
A37: Summary | B37: this page — the headline, where the savings come from, and by company
A38: Value Bridge | B38: step by step from disclosed capex to the saving; training vs inference; where each lever moves the needle
A39: Levers | B39: the five Helarctos levers in plain English, how sure we are of each, the scenario switch, training shares
A40: Microsoft / Alphabet / Amazon / Meta / Oracle / SpaceX | B40: each company's capex build from its filings (green = disclosed)
A41: Technical appendix | B41: Totals, Inputs, Sensitivity, CostLadder, ServingTraining, Evidence, Methodology — the full engineering ledger behind the levers
A43: Colours: yellow = assumption you can edit · green = disclosed filing / market data · blue = formula. Cash basis; FY2026 is company guidance; not investment advice.

Sheet Value Bridge
A1: VALUE BRIDGE — how the Helarctos architecture turns into dollars (FY2026, $B)
A2: Read top to bottom: what the six largest AI spenders spend, how their chip fleet splits between TRAINING models and INFERENCE (serving users), what Helarctos changes in each, and the dollars that follow. Every cell is a live formula; the levers live on the Levers tab.
A4: STEP 1 — What they spend on AI this year
A5: Total capex, all purposes | B5: ='Microsoft'!$C$3+'Alphabet'!$C$3+'Amazon'!$C$3+'Meta'!$C$3+'Oracle'!$C$3+'SpaceX'!$C$3 | D5: Company filings and guidance (green cells on each company tab).
A6: AI data-centre capex | B6: ='Microsoft'!$C$10+'Alphabet'!$C$10+'Amazon'!$C$10+'Meta'!$C$10+'Oracle'!$C$10+'SpaceX'!$C$10 | D6: Strips non-AI spend (e.g. Amazon retail logistics).
A7: …of which AI chips (GPUs, TPUs) | B7: =B70 | D7: The part Helarctos shrinks. Buildings, power and networking are NOT counted here (upside).
A8: Power & operations for those chips, per year | B8: =I70
A9: AI revenue | B9: =O70 | D9: Disclosed run-rates (Microsoft, Amazon) or estimates (others).
A10: Net AI cash result today | B10: =P70 | D10: AI revenue − AI capex − power. They are all losing money on AI today.
A12: STEP 2 — Split the chip fleet by what it does | C12: share
A13: Training fleet — builds new models | B13: =D70 | C13: =B13/B7 | D13: Estimated per company, 25%–55% (Levers tab); chip-weighted average shown.
A14: Inference fleet — answers users | B14: =E70 | C14: =B14/B7
A16: STEP 3 — TRAINING: fewer GPU-hours per model → smaller training clusters | C16: lever
A17: Training fleet capex today | B17: =B13
A18: Helarctos model is smaller for the same quality | C18: =SmallerModel | D18: fewer parameters to update at every step (lever 1)
A19: …so it needs fewer training tokens | C19: =FewerTokens | D19: compute-optimal training (lever 2)
A20: …at about the same speed per token | C20: =TrainSpeed | D20: comparable at the same size — no speed credit taken (lever 3)
A21: GPU-hours per training run fall by | C21: =TrainLever | D21: multiply the three
A22: Training fleet needed with Helarctos | B22: =B17/C21
A23: Training capex avoided | B23: =B17-B22
A24: Power & operations those GPUs would have drawn | B24: =J70 | D24: power scales with the fleet
A25: TRAINING SAVING (capex + power) | B25: =B23+B24
A26: ="How training savings become capex savings: labs size their training clusters to the GPU-hours their training runs need. If every model of a given quality needs ~"&TEXT(TrainLever,"0")&"× fewer GPU-hours, the same training programme runs on a cluster ~"&TEXT(TrainLever,"0")&"× smaller — the GPUs that never have to be bought are capex avoided, and the power they would have drawn is saved every year."
A28: STEP 4 — INFERENCE: less memory and more conversations per GPU → fewer inference GPUs | C28: lever
A29: Inference fleet capex today | B29: =B14
A30: Memory needed per conversation falls by | C30: =MemoryLever | D30: fixed-size state (lever 4)
A31: Compute needed per token falls by | C31: =ServeComputeLever | D31: smaller model × more conversations per GPU (levers 1 × 5)
A32: GPUs needed fall by — whichever limit binds | C32: =ServeGPULever | D32: the smaller of the two: a GPU is bought whole
A33: Inference fleet needed with Helarctos | B33: =B29/C32
A34: Inference capex avoided | B34: =B29-B33
A35: Power & operations those GPUs would have drawn | B35: =K70 | D35: power scales with the fleet
A36: INFERENCE SAVING (capex + power) | B36: =B34+B35 | D36: A GPU brings memory and compute together; the fleet must cover whichever runs out first. Transformers at long context run out of MEMORY (the growing KV cache) first.
A38: RESULT — FY2026
A39: Training (capex + power) | B39: =B25
A40: Inference (capex + power) | B40: =B36
A41: SPEND HELARCTOS MAKES UNNECESSARY, per year | B41: =B39+B40 | D41: Ties to the detail table total below.
A42: …as a share of all AI spend | B42: =B41/M70
A43: …as a share of the AI-chip bill | B43: =(B23+B34)/B7
A44: Net AI cash result with Helarctos | B44: =B10+B41
A45: Value of the saving, capitalized (÷ discount rate) | B45: =B41/Inputs!$B$6/1000 | D45: Simple perpetuity at the Inputs discount rate (6%).
A47: WHERE THE NEEDLE MOVES — switch the Helarctos levers on one at a time (FY2026)
A48: Step | B48: Training GPU-hours fall by | C48: Inference memory falls by | D48: Inference compute falls by | E48: Chip fleet cut (inference GPUs fall by the smaller) | F48: Spend cut, $B/yr | G48: Added by this step
A49: Today's transformer fleet | B49: 1 | C49: 1 | D49: 1 | E49: =(D70*(1-1/B49)+E70*(1-1/MIN(C49,D49)))/B70 | F49: =E49*(B70+I70) | G49: =F49
A50: Smaller model for the same quality (levers 1, 2) | B50: =SmallerModel^2 | C50: 1 | D50: =SmallerModel | E50: =(D70*(1-1/B50)+E70*(1-1/MIN(C50,D50)))/B70 | F50: =E50*(B70+I70) | G50: =F50-F49
A51: + Fixed-size memory per conversation (lever 4) | B51: =SmallerModel^2 | C51: =MemoryLever | D51: =SmallerModel | E51: =(D70*(1-1/B51)+E70*(1-1/MIN(C51,D51)))/B70 | F51: =E51*(B70+I70) | G51: =F51-F50
A52: + Many more conversations per GPU (lever 5) | B52: =TrainLever | C52: =MemoryLever | D52: =ServeComputeLever | E52: =(D70*(1-1/B52)+E70*(1-1/MIN(C52,D52)))/B70 | F52: =E52*(B70+I70) | G52: =F52-F51
A55: Read this as: the smaller model alone removes nearly all of the TRAINING bill (fewer parameters AND fewer tokens compound) but no inference GPUs — at long context a transformer's inference GPUs are full of memory (the growing KV cache), not busy computing, and a smaller model doesn't change that. Fixed-size memory unlocks inference, until compute becomes the limit; many more conversations per GPU lifts that limit. By then ~99% of the chip bill is gone: bigger multiples can't add much, because a cost can only fall to zero once. That is why this workbook reports dollars, not multiples. The order is the storyline; the end point does not depend on it.
A57: CROSS-CHECK against the technical Totals tab
A58: Totals tab, FY2026 spend cut (memory and compute priced separately, ~154×) | B58: =Totals!$F$13
A59: This bridge (training on GPU-hours, inference on whole GPUs) | B59: =B41
A60: Difference | B60: =B59-B58 | D60: Small by design: both remove ~99% of the chip bill. Totals also honours the Inputs datacenter-scaling toggle (default 0); this bridge counts chips only.
A62: DETAIL BY COMPANY — FY2026 (estimate) ($B). The engine behind every number above.
A63: Company | B63: AI-chip capex | C63: Training share | D63: Training fleet | E63: Inference fleet | F63: Training capex avoided | G63: Inference capex avoided | H63: Chip capex avoided | I63: Power & ops today | J63: Training power saved | K63: Inference power saved | L63: TOTAL spend cut | M63: AI spend (capex + power) | N63: % of AI spend cut | O63: AI revenue | P63: Net AI today | Q63: Net AI with Helarctos
A64: Microsoft | B64: ='Microsoft'!$C$12 | C64: =Levers!$C$22 | D64: =B64*C64 | E64: =B64-D64 | F64: =D64*(1-1/TrainLever) | G64: =E64*(1-1/ServeGPULever) | H64: =F64+G64 | I64: ='Microsoft'!$C$34 | J64: =IF(B64>0,I64*F64/B64,0) | K64: =IF(B64>0,I64*G64/B64,0) | L64: =H64+J64+K64 | M64: ='Microsoft'!$C$10+I64 | N64: =L64/M64 | O64: ='Microsoft'!$C$32 | P64: =O64-M64 | Q64: =P64+L64
A65: Alphabet | B65: ='Alphabet'!$C$12 | C65: =Levers!$C$23 | D65: =B65*C65 | E65: =B65-D65 | F65: =D65*(1-1/TrainLever) | G65: =E65*(1-1/ServeGPULever) | H65: =F65+G65 | I65: ='Alphabet'!$C$34 | J65: =IF(B65>0,I65*F65/B65,0) | K65: =IF(B65>0,I65*G65/B65,0) | L65: =H65+J65+K65 | M65: ='Alphabet'!$C$10+I65 | N65: =L65/M65 | O65: ='Alphabet'!$C$32 | P65: =O65-M65 | Q65: =P65+L65
A66: Amazon | B66: ='Amazon'!$C$12 | C66: =Levers!$C$24 | D66: =B66*C66 | E66: =B66-D66 | F66: =D66*(1-1/TrainLever) | G66: =E66*(1-1/ServeGPULever) | H66: =F66+G66 | I66: ='Amazon'!$C$34 | J66: =IF(B66>0,I66*F66/B66,0) | K66: =IF(B66>0,I66*G66/B66,0) | L66: =H66+J66+K66 | M66: ='Amazon'!$C$10+I66 | N66: =L66/M66 | O66: ='Amazon'!$C$32 | P66: =O66-M66 | Q66: =P66+L66
A67: Meta | B67: ='Meta'!$C$12 | C67: =Levers!$C$25 | D67: =B67*C67 | E67: =B67-D67 | F67: =D67*(1-1/TrainLever) | G67: =E67*(1-1/ServeGPULever) | H67: =F67+G67 | I67: ='Meta'!$C$34 | J67: =IF(B67>0,I67*F67/B67,0) | K67: =IF(B67>0,I67*G67/B67,0) | L67: =H67+J67+K67 | M67: ='Meta'!$C$10+I67 | N67: =L67/M67 | O67: ='Meta'!$C$32 | P67: =O67-M67 | Q67: =P67+L67
A68: Oracle | B68: ='Oracle'!$C$12 | C68: =Levers!$C$26 | D68: =B68*C68 | E68: =B68-D68 | F68: =D68*(1-1/TrainLever) | G68: =E68*(1-1/ServeGPULever) | H68: =F68+G68 | I68: ='Oracle'!$C$34 | J68: =IF(B68>0,I68*F68/B68,0) | K68: =IF(B68>0,I68*G68/B68,0) | L68: =H68+J68+K68 | M68: ='Oracle'!$C$10+I68 | N68: =L68/M68 | O68: ='Oracle'!$C$32 | P68: =O68-M68 | Q68: =P68+L68
A69: SpaceX | B69: ='SpaceX'!$C$12 | C69: =Levers!$C$27 | D69: =B69*C69 | E69: =B69-D69 | F69: =D69*(1-1/TrainLever) | G69: =E69*(1-1/ServeGPULever) | H69: =F69+G69 | I69: ='SpaceX'!$C$34 | J69: =IF(B69>0,I69*F69/B69,0) | K69: =IF(B69>0,I69*G69/B69,0) | L69: =H69+J69+K69 | M69: ='SpaceX'!$C$10+I69 | N69: =L69/M69 | O69: ='SpaceX'!$C$32 | P69: =O69-M69 | Q69: =P69+L69
A70: TOTAL (6) | B70: =SUM(B64:B69) | C70: =D70/B70 | D70: =SUM(D64:D69) | E70: =SUM(E64:E69) | F70: =SUM(F64:F69) | G70: =SUM(G64:G69) | H70: =SUM(H64:H69) | I70: =SUM(I64:I69) | J70: =SUM(J64:J69) | K70: =SUM(K64:K69) | ... M70: =SUM(M64:M69) | N70: =L70/M70 | O70: =SUM(O64:O69) | P70: =SUM(P64:P69) | Q70: =SUM(Q64:Q69)
A73: DETAIL BY COMPANY — FY2025 (actual) ($B). The engine behind every number above.
A74: Company | B74: AI-chip capex | C74: Training share | D74: Training fleet | E74: Inference fleet | F74: Training capex avoided | G74: Inference capex avoided | H74: Chip capex avoided | I74: Power & ops today | J74: Training power saved | K74: Inference power saved | L74: TOTAL spend cut | M74: AI spend (capex + power) | N74: % of AI spend cut | O74: AI revenue | P74: Net AI today | Q74: Net AI with Helarctos
A75: Microsoft | B75: ='Microsoft'!$B$12 | C75: =Levers!$C$22 | D75: =B75*C75 | E75: =B75-D75 | F75: =D75*(1-1/TrainLever) | G75: =E75*(1-1/ServeGPULever) | H75: =F75+G75 | I75: ='Microsoft'!$B$34 | J75: =IF(B75>0,I75*F75/B75,0) | K75: =IF(B75>0,I75*G75/B75,0) | L75: =H75+J75+K75 | M75: ='Microsoft'!$B$10+I75 | N75: =L75/M75 | O75: ='Microsoft'!$B$32 | P75: =O75-M75 | Q75: =P75+L75
A76: Alphabet | B76: ='Alphabet'!$B$12 | C76: =Levers!$C$23 | D76: =B76*C76 | E76: =B76-D76 | F76: =D76*(1-1/TrainLever) | G76: =E76*(1-1/ServeGPULever) | H76: =F76+G76 | I76: ='Alphabet'!$B$34 | J76: =IF(B76>0,I76*F76/B76,0) | K76: =IF(B76>0,I76*G76/B76,0) | L76: =H76+J76+K76 | M76: ='Alphabet'!$B$10+I76 | N76: =L76/M76 | O76: ='Alphabet'!$B$32 | P76: =O76-M76 | Q76: =P76+L76
A77: Amazon | B77: ='Amazon'!$B$12 | C77: =Levers!$C$24 | D77: =B77*C77 | E77: =B77-D77 | F77: =D77*(1-1/TrainLever) | G77: =E77*(1-1/ServeGPULever) | H77: =F77+G77 | I77: ='Amazon'!$B$34 | J77: =IF(B77>0,I77*F77/B77,0) | K77: =IF(B77>0,I77*G77/B77,0) | L77: =H77+J77+K77 | M77: ='Amazon'!$B$10+I77 | N77: =L77/M77 | O77: ='Amazon'!$B$32 | P77: =O77-M77 | Q77: =P77+L77
A78: Meta | B78: ='Meta'!$B$12 | C78: =Levers!$C$25 | D78: =B78*C78 | E78: =B78-D78 | F78: =D78*(1-1/TrainLever) | G78: =E78*(1-1/ServeGPULever) | H78: =F78+G78 | I78: ='Meta'!$B$34 | J78: =IF(B78>0,I78*F78/B78,0) | K78: =IF(B78>0,I78*G78/B78,0) | L78: =H78+J78+K78 | M78: ='Meta'!$B$10+I78 | N78: =L78/M78 | O78: ='Meta'!$B$32 | P78: =O78-M78 | Q78: =P78+L78
A79: Oracle | B79: ='Oracle'!$B$12 | C79: =Levers!$C$26 | D79: =B79*C79 | E79: =B79-D79 | F79: =D79*(1-1/TrainLever) | G79: =E79*(1-1/ServeGPULever) | H79: =F79+G79 | I79: ='Oracle'!$B$34 | J79: =IF(B79>0,I79*F79/B79,0) | K79: =IF(B79>0,I79*G79/B79,0) | L79: =H79+J79+K79 | M79: ='Oracle'!$B$10+I79 | N79: =L79/M79 | O79: ='Oracle'!$B$32 | P79: =O79-M79 | Q79: =P79+L79
A80: SpaceX | B80: ='SpaceX'!$B$12 | C80: =Levers!$C$27 | D80: =B80*C80 | E80: =B80-D80 | F80: =D80*(1-1/TrainLever) | G80: =E80*(1-1/ServeGPULever) | H80: =F80+G80 | I80: ='SpaceX'!$B$34 | J80: =IF(B80>0,I80*F80/B80,0) | K80: =IF(B80>0,I80*G80/B80,0) | L80: =H80+J80+K80 | M80: ='SpaceX'!$B$10+I80 | N80: =L80/M80 | O80: ='SpaceX'!$B$32 | P80: =O80-M80 | Q80: =P80+L80
A81: TOTAL (6) | B81: =SUM(B75:B80) | C81: =D81/B81 | D81: =SUM(D75:D80) | E81: =SUM(E75:E80) | F81: =SUM(F75:F80) | G81: =SUM(G75:G80) | H81: =SUM(H75:H80) | I81: =SUM(I75:I80) | J81: =SUM(J75:J80) | K81: =SUM(K75:K80) | ... M81: =SUM(M75:M80) | N81: =L81/M81 | O81: =SUM(O75:O80) | P81: =SUM(P75:P80) | Q81: =SUM(Q75:Q80)

Sheet Levers
A1: HELARCTOS LEVERS — the five things our architecture changes, in plain English
A2: Every dollar in this workbook comes from five levers. Each is shown with its value, how sure we are of it (MEASURED on our hardware runs, PROJECTED from measured trends, or an ESTIMATE / TARGET awaiting measurement), what it means, and which part of the AI bill it shrinks. Blue cells are linked to the technical Inputs tab; yellow cells are assumptions you can edit.
B4: Scenario (pick from the list) | C4: Today | D4: Today = the software kernels we have already built and measured. Optimized kernels = our funded kernel programme lands (a TARGET, not yet measured). The dollars differ by under 1%.
A6: # | B6: Lever | C6: Active | D6: Today | E6: Optimized kernels | F6: How sure are we? | G6: What it means | H6: Where it saves money
A7: 1 | B7: Smaller model for the same quality | C7: =IF(Scenario="Today",D7,E7) | D7: =Inputs!$B$23 | E7: =Inputs!$B$23 | F7: PROJECTED — trend fitted on models we trained (47M–663M parameters), extended to frontier scale | G7: We measured how quality improves with size for both architectures. Extending both trends, a Helarctos model matches a 1-trillion-parameter transformer with ~24% of the parameters — 4.2× fewer numbers to store, update and run. | H7: Training and inference compute
A8: 2 | B8: Fewer training tokens needed | C8: =IF(Scenario="Today",D8,E8) | D8: =D7 | E8: =E7 | F8: PROJECTED — standard compute-optimal scaling (training data grows in step with model size) | G8: Frontier labs train each model on data in proportion to its size. A model 4.2× smaller reaches its best quality on ~4.2× fewer tokens. | H8: Training
A9: 3 | B9: Training speed per token (same model size) | C9: =IF(Scenario="Today",D9,E9) | D9: 1 | E9: 1 | F9: ASSUMPTION — roughly comparable to a transformer; no speed credit taken | G9: At the same model size, Helarctos trains at roughly the same speed per token as a transformer, so we count no training speed-up. The training saving comes entirely from levers 1 and 2: a smaller model trained on fewer tokens. (Where Helarctos is much faster is inference — lever 5.) | H9: Training
A10: 4 | B10: Memory per live conversation | C10: =IF(Scenario="Today",D10,E10) | D10: =Inputs!$B$2 | E10: =Inputs!$B$2 | F10: MEASURED — 2,000× at 262k tokens; we use ÷100 to stay conservative | G10: A transformer keeps a memory (the 'KV cache') that grows with every token of every live conversation: ~197 KB per token, ~51 GB for one 262k-token conversation. Helarctos keeps a fixed-size state (~25 MB) however long the conversation gets. | H10: Inference GPUs (the memory limit)
A11: 5 | B11: More conversations served per GPU | C11: =IF(Scenario="Today",D11,E11) | D11: =Inputs!$B$24/Inputs!$B$23 | E11: =Inputs!$B$25/Inputs!$B$23 | F11: ESTIMATE — built on MEASURED concurrency and prompt-processing speed; per-token generation speed is an engineering estimate awaiting measurement | G11: Small per-conversation memory lets one GPU hold many long conversations at once (64 where a transformer fits 1–2 at 262k), and no growing cache is re-read for each new token. At the same model size: ~12× more tokens per GPU at an 8k-token average context, ~188× at 128k (used here), ~368× at 256k. | H11: Inference GPUs (the compute limit)
A13: HOW THE LEVERS COMBINE — one number per fleet
B14: Training: GPU-hours per training run fall by | C14: =SmallerModel*FewerTokens*TrainSpeed | D14: lever 1 × lever 2 × lever 3. Training clusters are sized to GPU-hours, so the training fleet can shrink by this much for the same training programme.
B15: Inference: memory needed per conversation falls by | C15: =MemoryLever | D15: lever 4
B16: Inference: compute needed per token falls by | C16: =SmallerModel*ServeThroughput | D16: lever 1 × lever 5
B17: Inference: GPUs needed fall by | C17: =MIN(MemoryLever,ServeComputeLever) | D17: A GPU is bought whole — memory and compute come together. The inference fleet has to cover whichever runs out first, so it shrinks by the SMALLER of the two levers (here the conservative ÷100 memory cap). Multiplying them (100 × 793 = 79,000×) would be wrong.
B18: For reference: technical tabs' blended inference cut | C18: =Inputs!$B$20 | D18: The technical appendix (Totals, company tabs) prices memory (~60% of a GPU's cost) and compute (~40%) separately and blends them (~154×). Same chip bill, under $1B apart on FY2026.
A20: TRAINING SHARE OF EACH COMPANY'S AI-CHIP FLEET — estimates (no company discloses this)
A21: Analysts put training at 30–45% of AI compute in 2026 (Gartner, Deloitte; the rest is inference, i.e. serving users). Per-company estimates below follow what each firm is known to be building.
B22: Microsoft | C22: 0.25 | D22: Inference-tilted: Azure serves the OpenAI API and Copilot; frontier training is moving to dedicated Stargate sites.
B23: Alphabet | C23: 0.35 | D23: Trains Gemini on TPUs, but runs the largest inference estate (Search, ads, Cloud).
B24: Amazon | C24: 0.35 | D24: Hosts large training clusters (Trainium) inside a broad AWS inference-rental business.
B25: Meta | C25: 0.45 | D25: FY26 capex raise is driven by frontier training clusters, on top of ads-ranking inference.
B26: Oracle | C26: 0.55 | D26: Stargate's dedicated OpenAI training data centres run on OCI.
B27: SpaceX | C27: 0.5 | D27: Greenfield build (Colossus); early workloads are training-heavy.
A29: FINE PRINT — what this does and does not claim
A30: • | B30: Only the AI chips (and the power they draw) are counted. The buildings, power infrastructure, cooling and networking around them would also shrink — that is upside, not in these numbers.
A31: • | B31: No memory credit is taken on training clusters: training is priced purely on GPU-hours.
A32: • | B32: Lever 1 is a projection: the quality trends are measured up to 663M parameters and extended to trillion-parameter scale.
A33: • | B33: The saving is spend no longer needed for the same AI output. In practice firms will likely reinvest it in more AI rather than cut budgets.
A34: • | B34: Cash basis. 'Capitalized' = annual saving ÷ discount rate (6%, roughly the long-bond yield).

Sheet Microsoft
A1: Microsoft — accelerator capex & value (FY2025 actual + FY2026 estimate)
A2: Metric | B2: FY2025 | C2: FY2026 | D2: basis / source
A3: Total capex ($B) | B3: 88 | C3: 190 | D3: FY25 capex incl leases ~$88B [DISCLOSED proxy]; FY26 ~$190B CY26 guide (Jul'26 restated to ~$175B capex+finance-leases on an accounting change -- the gross guide is kept here). Short-lived 'half'->'two-thirds' (CFO). Accel ~75% [BOM]. AI rev $37B run-rate (Q3 FY26).
A4: Infra / data-center share | B4: 0.97 | C4: 0.97 | D4: FILING: P&E note (FY25/FY26 10-K). Leasehold improvements, the only non-datacenter class, are $2.5B of $86.6B (FY25) and $4.2B of $133.1B (FY26) of gross additions -> 97%.
A5: Server / short-lived share | B5: 0.5 | C5: 0.67 | D5: CFO-disclosed (MSFT rose 50%->67%)
A6: Accelerator share within servers | B6: 0.75 | C6: 0.75 | D6: from BOM teardowns (~67-80%)
A7: Market cap ($B, approx) | B7: 3700 | D7: approximate June 2026 market data -- edit
A9: DERIVATION
A10: AI-infra capex ($B) | B10: =B3*B4 | C10: =C3*C4 | D10: total x infra share
A11: Server bucket ($B) | B11: =B10*B5 | C11: =C10*C5 | D11: infra x server share
A12: ACCELERATOR capex ($B) | B12: =B11*B6 | C12: =C11*C6 | D12: server x accel share
A13: Accel % of total capex | B13: =B12/B3 | C13: =C12/C3 | D13: varies across companies
A15: FLEET & OPERATING COST (from accelerator capex)
A16: Fleet size (GPU-equiv) | B16: =B12*1000000000/Inputs!$B$7 | C16: =C12*1000000000/Inputs!$B$7 | D16: accel capex / $ per GPU
A17: Total wall power (MW) | B17: =B16*Inputs!$B$8/1000 | C17: =C16*Inputs!$B$8/1000 | D17: GPUs x kW
A18: Daily energy (MWh) | B18: =B17*24 | C18: =C17*24
A19: Daily all-in opex ($/day) | B19: =B18*1000*Inputs!$B$9*(1+Inputs!$B$10) | C19: =C18*1000*Inputs!$B$9*(1+Inputs!$B$10) | D19: MWh x rate x (1+overhead)
A20: Annual opex ($M) | B20: =B19*365/1000000 | C20: =C19*365/1000000
A21: Lifetime opex ($B) | B21: =B20*Inputs!$B$11/1000 | C21: =C20*Inputs!$B$11/1000
A23: EFFICIENT VERSION & VALUE
A24: Efficient AI capex ($B) | B24: =B10-B25 | C24: =C10-C25 | D24: AI capex - avoided
A25: Capex avoided/yr ($B) | B25: =(B12+(B10-B12)*Inputs!$B$13)*(1-1/Inputs!$B$20) | C25: =(C12+(C10-C12)*Inputs!$B$13)*(1-1/Inputs!$B$20) | D25: accel + (datacenter x dc-scale), all x (1-1/reduction)
A26: Annual opex savings ($M) | B26: =B20*(1-1/Inputs!$B$5) | C26: =C20*(1-1/Inputs!$B$5)
A27: Sustained annual benefit ($B/yr) | B27: =B25+B26/1000 | C27: =C25+C26/1000 | D27: avoided + opex savings
A28: Capitalized value ($B) | B28: =B27/Inputs!$B$6 | C28: =C27/Inputs!$B$6 | D28: benefit / discount rate
A29: % of market cap | B29: =B28/$B$7 | C29: =C28/$B$7
A31: AI ECONOMICS (cash basis: AI revenue - AI capex - AI opex)
A32: AI revenue ($B) | B32: 30 | C32: 50 | D32: ESTIMATE (see Methodology). MSFT $37B & Amazon $15B run-rates disclosed; Google/Meta/SpaceX estimated.
A33: AI capex ($B) | B33: =B10 | C33: =C10 | D33: AI-infra capex (full: accel + buildings + power + net)
A34: AI opex ($B) | B34: =B20/1000 | C34: =C20/1000 | D34: annual power/operating
A35: Net AI NOW ($B) | B35: =B32-B33-B34 | C35: =C32-C33-C34 | D35: revenue - capex - opex (cash burn)
A36: Spend cut, our arch ($B) | B36: =B27 | C36: =C27 | D36: accel capex avoided + opex saved
A37: Net AI WITH our arch ($B) | B37: =B35+B36 | C37: =C35+C36 | D37: Net AI now + spend cut
A38: % AI spend reduction | B38: =B36/(B33+B34) | C38: =C36/(C33+C34) | D38: spend cut / total AI spend (accel-only; upside if DC scales)
A40: SOURCES & REFERENCES
A41: FY25 capex >$88B incl leases; server life 2-6yr (FY25 10-K) | B41: https://www.sec.gov/Archives/edgar/data/789019/000095017025100235/msft-20250630.htm
A42: FY26 ~$190B guide; 'two-thirds' short-lived = GPUs+CPUs (Q3 FY26 call) | B42: https://www.fool.com/earnings/call-transcripts/2026/04/29/microsoft-msft-q3-2026-earnings-transcript/
A43: AI revenue $37B annual run-rate (Q3 FY26) | B43: https://news.alphastreet.com/microsoft-msft-q3-fy2026-azure-hits-40-growth-as-ai-business-reaches-37-billion-run-rate/
A44: ~485k Hopper GPUs / ~$31B in 2024 (Omdia) - cross-checks accel capex | B44: https://techcrunch.com/2024/12/18/microsoft-bought-nearly-500000-nvidia-hopper-chips-this-year/

Sheet Alphabet
A1: Alphabet — accelerator capex & value (FY2025 actual + FY2026 estimate)
A2: Metric | B2: FY2025 | C2: FY2026 | D2: basis / source
A3: Total capex ($B) | B3: 91.4 | C3: 185 | D3: FY25 capex $91.4B [DISCLOSED]; FY26 $180-190B guide. 60% servers / 40% DC (CFO). Accel ~67% [BOM]. AI rev ESTIMATE (Cloud $70B run-rate, AI subset).
A4: Infra / data-center share | B4: 0.93 | C4: 0.95 | D4: FILING: P&E note. Technical infrastructure +$61.8B vs office space +$2.9B and corporate +$1.9B in 2025 (10-K) -> 93%; +$43.5B vs +$2.3B office in H1 2026 (10-Q) -> 95%.
A5: Server / short-lived share | B5: 0.6 | C5: 0.6 | D5: CFO-disclosed (MSFT rose 50%->67%)
A6: Accelerator share within servers | B6: 0.67 | C6: 0.67 | D6: from BOM teardowns (~67-80%)
A7: Market cap ($B, approx) | B7: 4250 | D7: approximate June 2026 market data -- edit
A9: DERIVATION
A10: AI-infra capex ($B) | B10: =B3*B4 | C10: =C3*C4 | D10: total x infra share
A11: Server bucket ($B) | B11: =B10*B5 | C11: =C10*C5 | D11: infra x server share
A12: ACCELERATOR capex ($B) | B12: =B11*B6 | C12: =C11*C6 | D12: server x accel share
A13: Accel % of total capex | B13: =B12/B3 | C13: =C12/C3 | D13: varies across companies
A15: FLEET & OPERATING COST (from accelerator capex)
A16: Fleet size (GPU-equiv) | B16: =B12*1000000000/Inputs!$B$7 | C16: =C12*1000000000/Inputs!$B$7 | D16: accel capex / $ per GPU
A17: Total wall power (MW) | B17: =B16*Inputs!$B$8/1000 | C17: =C16*Inputs!$B$8/1000 | D17: GPUs x kW
A18: Daily energy (MWh) | B18: =B17*24 | C18: =C17*24
A19: Daily all-in opex ($/day) | B19: =B18*1000*Inputs!$B$9*(1+Inputs!$B$10) | C19: =C18*1000*Inputs!$B$9*(1+Inputs!$B$10) | D19: MWh x rate x (1+overhead)
A20: Annual opex ($M) | B20: =B19*365/1000000 | C20: =C19*365/1000000
A21: Lifetime opex ($B) | B21: =B20*Inputs!$B$11/1000 | C21: =C20*Inputs!$B$11/1000
A23: EFFICIENT VERSION & VALUE
A24: Efficient AI capex ($B) | B24: =B10-B25 | C24: =C10-C25 | D24: AI capex - avoided
A25: Capex avoided/yr ($B) | B25: =(B12+(B10-B12)*Inputs!$B$13)*(1-1/Inputs!$B$20) | C25: =(C12+(C10-C12)*Inputs!$B$13)*(1-1/Inputs!$B$20) | D25: accel + (datacenter x dc-scale), all x (1-1/reduction)
A26: Annual opex savings ($M) | B26: =B20*(1-1/Inputs!$B$5) | C26: =C20*(1-1/Inputs!$B$5)
A27: Sustained annual benefit ($B/yr) | B27: =B25+B26/1000 | C27: =C25+C26/1000 | D27: avoided + opex savings
A28: Capitalized value ($B) | B28: =B27/Inputs!$B$6 | C28: =C27/Inputs!$B$6 | D28: benefit / discount rate
A29: % of market cap | B29: =B28/$B$7 | C29: =C28/$B$7
A31: AI ECONOMICS (cash basis: AI revenue - AI capex - AI opex)
A32: AI revenue ($B) | B32: 25 | C32: 40 | D32: ESTIMATE (see Methodology). MSFT $37B & Amazon $15B run-rates disclosed; Google/Meta/SpaceX estimated.
A33: AI capex ($B) | B33: =B10 | C33: =C10 | D33: AI-infra capex (full: accel + buildings + power + net)
A34: AI opex ($B) | B34: =B20/1000 | C34: =C20/1000 | D34: annual power/operating
A35: Net AI NOW ($B) | B35: =B32-B33-B34 | C35: =C32-C33-C34 | D35: revenue - capex - opex (cash burn)
A36: Spend cut, our arch ($B) | B36: =B27 | C36: =C27 | D36: accel capex avoided + opex saved
A37: Net AI WITH our arch ($B) | B37: =B35+B36 | C37: =C35+C36 | D37: Net AI now + spend cut
A38: % AI spend reduction | B38: =B36/(B33+B34) | C38: =C36/(C33+C34) | D38: spend cut / total AI spend (accel-only; upside if DC scales)
A40: SOURCES & REFERENCES
A41: FY25 capex $91.4B; CFO 60% servers / 40% DC+net (Q4'25 call) | B41: https://www.fool.com/earnings/call-transcripts/2026/02/04/alphabet-googl-q4-2025-earnings-call-transcript/
A42: FY26 guide $180-190B (Q1'26) | B42: https://www.cnbc.com/2026/04/29/alphabet-googl-q1-2026-earnings.html
A43: Server life 6yr; TPU at-cost TCO 20-50% below NVIDIA (SemiAnalysis) | B43: https://newsletter.semianalysis.com/p/tpuv7-google-takes-a-swing-at-the

Sheet Amazon
A1: Amazon — accelerator capex & value (FY2025 actual + FY2026 estimate)
A2: Metric | B2: FY2025 | C2: FY2026 | D2: basis / source
A3: Total capex ($B) | B3: 128.3 | C3: 220 | D3: FY25 cash capex $128.3B [DISCLOSED]; FY26 raised to ~$220B (Q2'26, 2026-07-30). AWS ~68-70% -> strips fulfillment. Accel ~67% [BOM]. AI rev >$15B AWS run-rate (Q1 FY26, Jassy).
A4: Infra / data-center share | B4: 0.68 | C4: 0.76 | D4: FILING: segment note, AWS share of net P&E additions. $96.5B of $142.4B in 2025 (10-K) -> 68%; $90.1B of $118.6B in H1 2026 (10-Q) -> 76%. Strips fulfillment/logistics.
A5: Server / short-lived share | B5: 0.65 | C5: 0.65 | D5: CFO-disclosed (MSFT rose 50%->67%)
A6: Accelerator share within servers | B6: 0.67 | C6: 0.67 | D6: from BOM teardowns (~67-80%)
A7: Market cap ($B, approx) | B7: 2830 | D7: approximate June 2026 market data -- edit
A9: DERIVATION
A10: AI-infra capex ($B) | B10: =B3*B4 | C10: =C3*C4 | D10: total x infra share
A11: Server bucket ($B) | B11: =B10*B5 | C11: =C10*C5 | D11: infra x server share
A12: ACCELERATOR capex ($B) | B12: =B11*B6 | C12: =C11*C6 | D12: server x accel share
A13: Accel % of total capex | B13: =B12/B3 | C13: =C12/C3 | D13: varies across companies
A15: FLEET & OPERATING COST (from accelerator capex)
A16: Fleet size (GPU-equiv) | B16: =B12*1000000000/Inputs!$B$7 | C16: =C12*1000000000/Inputs!$B$7 | D16: accel capex / $ per GPU
A17: Total wall power (MW) | B17: =B16*Inputs!$B$8/1000 | C17: =C16*Inputs!$B$8/1000 | D17: GPUs x kW
A18: Daily energy (MWh) | B18: =B17*24 | C18: =C17*24
A19: Daily all-in opex ($/day) | B19: =B18*1000*Inputs!$B$9*(1+Inputs!$B$10) | C19: =C18*1000*Inputs!$B$9*(1+Inputs!$B$10) | D19: MWh x rate x (1+overhead)
A20: Annual opex ($M) | B20: =B19*365/1000000 | C20: =C19*365/1000000
A21: Lifetime opex ($B) | B21: =B20*Inputs!$B$11/1000 | C21: =C20*Inputs!$B$11/1000
A23: EFFICIENT VERSION & VALUE
A24: Efficient AI capex ($B) | B24: =B10-B25 | C24: =C10-C25 | D24: AI capex - avoided
A25: Capex avoided/yr ($B) | B25: =(B12+(B10-B12)*Inputs!$B$13)*(1-1/Inputs!$B$20) | C25: =(C12+(C10-C12)*Inputs!$B$13)*(1-1/Inputs!$B$20) | D25: accel + (datacenter x dc-scale), all x (1-1/reduction)
A26: Annual opex savings ($M) | B26: =B20*(1-1/Inputs!$B$5) | C26: =C20*(1-1/Inputs!$B$5)
A27: Sustained annual benefit ($B/yr) | B27: =B25+B26/1000 | C27: =C25+C26/1000 | D27: avoided + opex savings
A28: Capitalized value ($B) | B28: =B27/Inputs!$B$6 | C28: =C27/Inputs!$B$6 | D28: benefit / discount rate
A29: % of market cap | B29: =B28/$B$7 | C29: =C28/$B$7
A31: AI ECONOMICS (cash basis: AI revenue - AI capex - AI opex)
A32: AI revenue ($B) | B32: 12 | C32: 22 | D32: ESTIMATE (see Methodology). MSFT $37B & Amazon $15B run-rates disclosed; Google/Meta/SpaceX estimated.
A33: AI capex ($B) | B33: =B10 | C33: =C10 | D33: AI-infra capex (full: accel + buildings + power + net)
A34: AI opex ($B) | B34: =B20/1000 | C34: =C20/1000 | D34: annual power/operating
A35: Net AI NOW ($B) | B35: =B32-B33-B34 | C35: =C32-C33-C34 | D35: revenue - capex - opex (cash burn)
A36: Spend cut, our arch ($B) | B36: =B27 | C36: =C27 | D36: accel capex avoided + opex saved
A37: Net AI WITH our arch ($B) | B37: =B35+B36 | C37: =C35+C36 | D37: Net AI now + spend cut
A38: % AI spend reduction | B38: =B36/(B33+B34) | C38: =C36/(C33+C34) | D38: spend cut / total AI spend (accel-only; upside if DC scales)
A40: SOURCES & REFERENCES
A41: FY25 cash capex $128.3B; AWS 67.8% of net P&E adds; server life 6->5yr (FY25 10-K) | B41: https://www.sec.gov/Archives/edgar/data/1018724/000101872426000004/amzn-20251231.htm
A42: ~$200B 2026 capex, 'predominantly AWS' (Q4'25 call) | B42: https://www.fool.com/earnings/call-transcripts/2026/02/05/amazon-amzn-q4-2025-earnings-call-transcript/
A43: AWS AI revenue >$15B annual run-rate (Q1'26, Jassy) | B43: https://www.bnnbloomberg.ca/business/artificial-intelligence/2026/04/09/amazon-cloud-units-ai-revenue-run-rate-exceeds-us15-billion-in-first-quarter-ceo-says/

Sheet Meta
A1: Meta — accelerator capex & value (FY2025 actual + FY2026 estimate)
A2: Metric | B2: FY2025 | C2: FY2026 | D2: basis / source
A3: Total capex ($B) | B3: 72.2 | C3: 137.5 | D3: FY25 capex incl leases $72.2B [DISCLOSED]; FY26 $130-145B guide (mid 137.5). Accel ~74% [BOM]. AI rev DIRECT est ~$4B -- Meta's real AI payoff is INDIRECT ad-uplift (~$20B), not counted.
A4: Infra / data-center share | B4: 0.95 | C4: 0.98 | D4: FILING: Note 6 P&E. Leasehold improvements + equipment and other are $3.3B of $69.1B gross additions in 2025 (10-K) -> 95%; $0.95B of $59.1B in H1 2026 (10-Q) -> 98%.
A5: Server / short-lived share | B5: 0.65 | C5: 0.65 | D5: CFO-disclosed (MSFT rose 50%->67%)
A6: Accelerator share within servers | B6: 0.74 | C6: 0.74 | D6: from BOM teardowns (~67-80%)
A7: Market cap ($B, approx) | B7: 1490 | D7: approximate June 2026 market data -- edit
A9: DERIVATION
A10: AI-infra capex ($B) | B10: =B3*B4 | C10: =C3*C4 | D10: total x infra share
A11: Server bucket ($B) | B11: =B10*B5 | C11: =C10*C5 | D11: infra x server share
A12: ACCELERATOR capex ($B) | B12: =B11*B6 | C12: =C11*C6 | D12: server x accel share
A13: Accel % of total capex | B13: =B12/B3 | C13: =C12/C3 | D13: varies across companies
A15: FLEET & OPERATING COST (from accelerator capex)
A16: Fleet size (GPU-equiv) | B16: =B12*1000000000/Inputs!$B$7 | C16: =C12*1000000000/Inputs!$B$7 | D16: accel capex / $ per GPU
A17: Total wall power (MW) | B17: =B16*Inputs!$B$8/1000 | C17: =C16*Inputs!$B$8/1000 | D17: GPUs x kW
A18: Daily energy (MWh) | B18: =B17*24 | C18: =C17*24
A19: Daily all-in opex ($/day) | B19: =B18*1000*Inputs!$B$9*(1+Inputs!$B$10) | C19: =C18*1000*Inputs!$B$9*(1+Inputs!$B$10) | D19: MWh x rate x (1+overhead)
A20: Annual opex ($M) | B20: =B19*365/1000000 | C20: =C19*365/1000000
A21: Lifetime opex ($B) | B21: =B20*Inputs!$B$11/1000 | C21: =C20*Inputs!$B$11/1000
A23: EFFICIENT VERSION & VALUE
A24: Efficient AI capex ($B) | B24: =B10-B25 | C24: =C10-C25 | D24: AI capex - avoided
A25: Capex avoided/yr ($B) | B25: =(B12+(B10-B12)*Inputs!$B$13)*(1-1/Inputs!$B$20) | C25: =(C12+(C10-C12)*Inputs!$B$13)*(1-1/Inputs!$B$20) | D25: accel + (datacenter x dc-scale), all x (1-1/reduction)
A26: Annual opex savings ($M) | B26: =B20*(1-1/Inputs!$B$5) | C26: =C20*(1-1/Inputs!$B$5)
A27: Sustained annual benefit ($B/yr) | B27: =B25+B26/1000 | C27: =C25+C26/1000 | D27: avoided + opex savings
A28: Capitalized value ($B) | B28: =B27/Inputs!$B$6 | C28: =C27/Inputs!$B$6 | D28: benefit / discount rate
A29: % of market cap | B29: =B28/$B$7 | C29: =C28/$B$7
A31: AI ECONOMICS (cash basis: AI revenue - AI capex - AI opex)
A32: AI revenue ($B) | B32: 4 | C32: 8 | D32: ESTIMATE (see Methodology). MSFT $37B & Amazon $15B run-rates disclosed; Google/Meta/SpaceX estimated.
A33: AI capex ($B) | B33: =B10 | C33: =C10 | D33: AI-infra capex (full: accel + buildings + power + net)
A34: AI opex ($B) | B34: =B20/1000 | C34: =C20/1000 | D34: annual power/operating
A35: Net AI NOW ($B) | B35: =B32-B33-B34 | C35: =C32-C33-C34 | D35: revenue - capex - opex (cash burn)
A36: Spend cut, our arch ($B) | B36: =B27 | C36: =C27 | D36: accel capex avoided + opex saved
A37: Net AI WITH our arch ($B) | B37: =B35+B36 | C37: =C35+C36 | D37: Net AI now + spend cut
A38: % AI spend reduction | B38: =B36/(B33+B34) | C38: =C36/(C33+C34) | D38: spend cut / total AI spend (accel-only; upside if DC scales)
A40: SOURCES & REFERENCES
A41: FY25 capex $72.2B incl finance leases (Q4/FY25 release) | B41: https://investor.atmeta.com/investor-news/press-release-details/2026/Meta-Reports-Fourth-Quarter-and-Full-Year-2025-Results/default.aspx
A42: FY26 $125-145B guide; raise driven by HBM pricing (Q1'26 call) | B42: https://www.fool.com/earnings/call-transcripts/2026/04/29/meta-meta-q1-2026-earnings-call-transcript/
A43: >1.3M GPUs by end-2025 (Zuckerberg) - cross-checks accel capex | B43: https://techcrunch.com/2025/01/24/mark-zuckerberg-says-meta-will-have-1-3m-gpus-for-ai-by-year-end/
A44: Server life 5.5yr (-$2.9B depreciation) | B44: https://www.thestack.technology/meta-extends-server-life-again-saving-it-2-9-billion/
A45: ~25% of capex to NVIDIA (Bloomberg) - accel-share basis | B45: https://finance.yahoo.com/news/big-techs-spending-drove-nvidias-rise-154027146.html

Sheet Oracle
A1: Oracle — accelerator capex & value (FY2025 actual + FY2026 estimate)
A2: Metric | B2: FY2025 | C2: FY2026 | D2: basis / source
A3: Total capex ($B) | B3: 21.2 | C3: 55.7 | D3: FY25 capex $21.2B [DISCLOSED 10-K]; FY26 ACTUAL $55.7B (reported 2026-06-10; FY27 guide ~$70B net / up to $95B gross). Capex ~all OCI/GPU data centers. Accel ~70% [BOM]. AI rev = OCI/GPU cloud (IaaS ~$12B r/r Q4 FY25; AI subset, EST).
A4: Infra / data-center share | B4: 0.85 | C4: 0.9 | D4: ESTIMATE: the P&E note has no office line (buildings mix datacenters with the Nashville HQ build); capex growth is 'primarily due to the expansion of our data centers' (FY26 10-K).
A5: Server / short-lived share | B5: 0.75 | C5: 0.75 | D5: CFO-disclosed (MSFT rose 50%->67%)
A6: Accelerator share within servers | B6: 0.7 | C6: 0.7 | D6: from BOM teardowns (~67-80%)
A7: Market cap ($B, approx) | B7: 433 | D7: approximate June 2026 market data -- edit
A9: DERIVATION
A10: AI-infra capex ($B) | B10: =B3*B4 | C10: =C3*C4 | D10: total x infra share
A11: Server bucket ($B) | B11: =B10*B5 | C11: =C10*C5 | D11: infra x server share
A12: ACCELERATOR capex ($B) | B12: =B11*B6 | C12: =C11*C6 | D12: server x accel share
A13: Accel % of total capex | B13: =B12/B3 | C13: =C12/C3 | D13: varies across companies
A15: FLEET & OPERATING COST (from accelerator capex)
A16: Fleet size (GPU-equiv) | B16: =B12*1000000000/Inputs!$B$7 | C16: =C12*1000000000/Inputs!$B$7 | D16: accel capex / $ per GPU
A17: Total wall power (MW) | B17: =B16*Inputs!$B$8/1000 | C17: =C16*Inputs!$B$8/1000 | D17: GPUs x kW
A18: Daily energy (MWh) | B18: =B17*24 | C18: =C17*24
A19: Daily all-in opex ($/day) | B19: =B18*1000*Inputs!$B$9*(1+Inputs!$B$10) | C19: =C18*1000*Inputs!$B$9*(1+Inputs!$B$10) | D19: MWh x rate x (1+overhead)
A20: Annual opex ($M) | B20: =B19*365/1000000 | C20: =C19*365/1000000
A21: Lifetime opex ($B) | B21: =B20*Inputs!$B$11/1000 | C21: =C20*Inputs!$B$11/1000
A23: EFFICIENT VERSION & VALUE
A24: Efficient AI capex ($B) | B24: =B10-B25 | C24: =C10-C25 | D24: AI capex - avoided
A25: Capex avoided/yr ($B) | B25: =(B12+(B10-B12)*Inputs!$B$13)*(1-1/Inputs!$B$20) | C25: =(C12+(C10-C12)*Inputs!$B$13)*(1-1/Inputs!$B$20) | D25: accel + (datacenter x dc-scale), all x (1-1/reduction)
A26: Annual opex savings ($M) | B26: =B20*(1-1/Inputs!$B$5) | C26: =C20*(1-1/Inputs!$B$5)
A27: Sustained annual benefit ($B/yr) | B27: =B25+B26/1000 | C27: =C25+C26/1000 | D27: avoided + opex savings
A28: Capitalized value ($B) | B28: =B27/Inputs!$B$6 | C28: =C27/Inputs!$B$6 | D28: benefit / discount rate
A29: % of market cap | B29: =B28/$B$7 | C29: =C28/$B$7
A31: AI ECONOMICS (cash basis: AI revenue - AI capex - AI opex)
A32: AI revenue ($B) | B32: 8 | C32: 15 | D32: ESTIMATE (see Methodology). MSFT $37B & Amazon $15B run-rates disclosed; Google/Meta/SpaceX estimated.
A33: AI capex ($B) | B33: =B10 | C33: =C10 | D33: AI-infra capex (full: accel + buildings + power + net)
A34: AI opex ($B) | B34: =B20/1000 | C34: =C20/1000 | D34: annual power/operating
A35: Net AI NOW ($B) | B35: =B32-B33-B34 | C35: =C32-C33-C34 | D35: revenue - capex - opex (cash burn)
A36: Spend cut, our arch ($B) | B36: =B27 | C36: =C27 | D36: accel capex avoided + opex saved
A37: Net AI WITH our arch ($B) | B37: =B35+B36 | C37: =C35+C36 | D37: Net AI now + spend cut
A38: % AI spend reduction | B38: =B36/(B33+B34) | C38: =C36/(C33+C34) | D38: spend cut / total AI spend (accel-only; upside if DC scales)
A40: SOURCES & REFERENCES
A41: FY25 capex $21.2B; FY26 ~$50B guide on $67B rev (CIO Dive) | B41: https://www.ciodive.com/news/oracle-capex-spike-cloud-ai-data-center/807721/
A42: OCI run-rate ~$27B exiting FY25; IaaS $3.0B Q4 +52%; RPO $138B (Q4 FY25) | B42: https://futurumgroup.com/insights/oracle-delivers-q4-fy-2025-results-with-27-cloud-growth-rpo-hits-138-billion/
A43: FY26 OCI +77% to ~$18B; RPO $523B +433% on AI deals (Q2 FY26) | B43: https://futurumgroup.com/insights/oracle-q2-fy-2026-cloud-grows-capex-rises-for-ai-buildout/

Sheet SpaceX
A1: SpaceX — accelerator capex & value (FY2025 actual + FY2026 estimate)
A2: Metric | B2: FY2025 | C2: FY2026 | D2: basis / source
A3: Total capex ($B) | B3: 12.7 | C3: 55 | D3: FY25 S-1 AI capex $12.7B [DISCLOSED]; FY26 ~$55B EST from H1'26 DISCLOSED $23.5B (Q1 $7.7B, Q2 $15.8B; 82.7% of total capex) + company guiding capex roughly flat Q3/Q4. ~all accelerator (greenfield COLOSSUS I/II). AI rev ~0 today; Anthropic (up to $1.25B/mo) and Google (up to $920M/mo) compute deals ramp from 2027.
A4: Infra / data-center share | B4: 1 | C4: 1 | D4: FILING: capex is the AI segment's own figure (S-1; Q2 2026 10-Q segment note, $23.6B in H1 2026).
A5: Server / short-lived share | B5: 0.79 | C5: 0.79 | D5: CFO-disclosed (MSFT rose 50%->67%)
A6: Accelerator share within servers | B6: 1 | C6: 1 | D6: from BOM teardowns (~67-80%)
A7: Market cap ($B, approx) | B7: 1950 | D7: approximate June 2026 market data -- edit
A9: DERIVATION
A10: AI-infra capex ($B) | B10: =B3*B4 | C10: =C3*C4 | D10: total x infra share
A11: Server bucket ($B) | B11: =B10*B5 | C11: =C10*C5 | D11: infra x server share
A12: ACCELERATOR capex ($B) | B12: =B11*B6 | C12: =C11*C6 | D12: server x accel share
A13: Accel % of total capex | B13: =B12/B3 | C13: =C12/C3 | D13: varies across companies
A15: FLEET & OPERATING COST (from accelerator capex)
A16: Fleet size (GPU-equiv) | B16: =B12*1000000000/Inputs!$B$7 | C16: =C12*1000000000/Inputs!$B$7 | D16: accel capex / $ per GPU
A17: Total wall power (MW) | B17: =B16*Inputs!$B$8/1000 | C17: =C16*Inputs!$B$8/1000 | D17: GPUs x kW
A18: Daily energy (MWh) | B18: =B17*24 | C18: =C17*24
A19: Daily all-in opex ($/day) | B19: =B18*1000*Inputs!$B$9*(1+Inputs!$B$10) | C19: =C18*1000*Inputs!$B$9*(1+Inputs!$B$10) | D19: MWh x rate x (1+overhead)
A20: Annual opex ($M) | B20: =B19*365/1000000 | C20: =C19*365/1000000
A21: Lifetime opex ($B) | B21: =B20*Inputs!$B$11/1000 | C21: =C20*Inputs!$B$11/1000
A23: EFFICIENT VERSION & VALUE
A24: Efficient AI capex ($B) | B24: =B10-B25 | C24: =C10-C25 | D24: AI capex - avoided
A25: Capex avoided/yr ($B) | B25: =(B12+(B10-B12)*Inputs!$B$13)*(1-1/Inputs!$B$20) | C25: =(C12+(C10-C12)*Inputs!$B$13)*(1-1/Inputs!$B$20) | D25: accel + (datacenter x dc-scale), all x (1-1/reduction)
A26: Annual opex savings ($M) | B26: =B20*(1-1/Inputs!$B$5) | C26: =C20*(1-1/Inputs!$B$5)
A27: Sustained annual benefit ($B/yr) | B27: =B25+B26/1000 | C27: =C25+C26/1000 | D27: avoided + opex savings
A28: Capitalized value ($B) | B28: =B27/Inputs!$B$6 | C28: =C27/Inputs!$B$6 | D28: benefit / discount rate
A29: % of market cap | B29: =B28/$B$7 | C29: =C28/$B$7
A31: AI ECONOMICS (cash basis: AI revenue - AI capex - AI opex)
A32: AI revenue ($B) | B32: 0.3 | C32: 1 | D32: ESTIMATE (see Methodology). MSFT $37B & Amazon $15B run-rates disclosed; Google/Meta/SpaceX estimated.
A33: AI capex ($B) | B33: =B10 | C33: =C10 | D33: AI-infra capex (full: accel + buildings + power + net)
A34: AI opex ($B) | B34: =B20/1000 | C34: =C20/1000 | D34: annual power/operating
A35: Net AI NOW ($B) | B35: =B32-B33-B34 | C35: =C32-C33-C34 | D35: revenue - capex - opex (cash burn)
A36: Spend cut, our arch ($B) | B36: =B27 | C36: =C27 | D36: accel capex avoided + opex saved
A37: Net AI WITH our arch ($B) | B37: =B35+B36 | C37: =C35+C36 | D37: Net AI now + spend cut
A38: % AI spend reduction | B38: =B36/(B33+B34) | C38: =C36/(C33+C34) | D38: spend cut / total AI spend (accel-only; upside if DC scales)
A40: SOURCES & REFERENCES
A41: S-1 registration statement (SEC EDGAR) | B41: https://www.sec.gov/Archives/edgar/data/1181412/000162828026036936/spaceexplorationtechnologi.htm
A42: S-1 financials & AI breakdown (Hargreaves Lansdown) | B42: https://www.hl.co.uk/news/inside-spacexs-ipo-filing-revenue-starlink-ai-and-key-financials
A43: $12.7B AI capex = ~60% of capex; COLOSSUS buildout (Investing.com) | B43: https://www.investing.com/analysis/spacex-is-quietly-becoming-an-ai-compute-and-orbital-infrastructure-company-200681776
A44: AI1 orbital data centers; Anthropic as compute customer (DCD) | B44: https://www.datacenterdynamics.com/en/news/spacex-ipo-musks-firm-set-to-launch-first-orbital-data-center-ai1-satellites-in-2027-will-put-compute-on-starlink-craft/

Sheet Totals
A1: 6-COMPANY AI ECONOMICS — current AI cash burn & the effect of our architecture
A2: They all spend far more on AI (capex + opex) than they earn from it -- they are losing money on AI today. Our architecture cuts the accelerator spend ~95%, shrinking the burn. The named firms are a floor; a GLOBAL estimate grosses up for the rest. Yellow assumption cells (also sliders in the app) and green disclosed-data cells live on company tabs.
A4: NET AI ECONOMICS — FY2025 (cash basis: AI revenue - AI capex - AI opex)
A5: Company | B5: AI revenue ($B) | C5: AI capex ($B) | D5: AI opex ($B) | E5: Net AI NOW ($B) | F5: Spend cut, our arch ($B) | G5: Net AI W/ ARCH ($B) | H5: % spend cut
A6: Microsoft | B6: =Microsoft!$B$32 | C6: =Microsoft!$B$33 | D6: =Microsoft!$B$34 | E6: =Microsoft!$B$35 | F6: =Microsoft!$B$36 | G6: =Microsoft!$B$37 | H6: =Microsoft!$B$38
A7: Alphabet | B7: =Alphabet!$B$32 | C7: =Alphabet!$B$33 | D7: =Alphabet!$B$34 | E7: =Alphabet!$B$35 | F7: =Alphabet!$B$36 | G7: =Alphabet!$B$37 | H7: =Alphabet!$B$38
A8: Amazon | B8: =Amazon!$B$32 | C8: =Amazon!$B$33 | D8: =Amazon!$B$34 | E8: =Amazon!$B$35 | F8: =Amazon!$B$36 | G8: =Amazon!$B$37 | H8: =Amazon!$B$38
A9: Meta | B9: =Meta!$B$32 | C9: =Meta!$B$33 | D9: =Meta!$B$34 | E9: =Meta!$B$35 | F9: =Meta!$B$36 | G9: =Meta!$B$37 | H9: =Meta!$B$38
A10: Oracle | B10: =Oracle!$B$32 | C10: =Oracle!$B$33 | D10: =Oracle!$B$34 | E10: =Oracle!$B$35 | F10: =Oracle!$B$36 | G10: =Oracle!$B$37 | H10: =Oracle!$B$38
A11: SpaceX | B11: =SpaceX!$B$32 | C11: =SpaceX!$B$33 | D11: =SpaceX!$B$34 | E11: =SpaceX!$B$35 | F11: =SpaceX!$B$36 | G11: =SpaceX!$B$37 | H11: =SpaceX!$B$38
A12: TOTAL (6) | B12: =SUM(B6:B11) | C12: =SUM(C6:C11) | D12: =SUM(D6:D11) | E12: =SUM(E6:E11) | F12: =SUM(F6:F11) | G12: =SUM(G6:G11) | H12: =F12/(C12+D12)
A13: FY2026 (estimate) | E13: =SUM(Microsoft!$C$35,Alphabet!$C$35,Amazon!$C$35,Meta!$C$35,Oracle!$C$35,SpaceX!$C$35) | F13: =SUM(Microsoft!$C$36,Alphabet!$C$36,Amazon!$C$36,Meta!$C$36,Oracle!$C$36,SpaceX!$C$36) | G13: =SUM(Microsoft!$C$37,Alphabet!$C$37,Amazon!$C$37,Meta!$C$37,Oracle!$C$37,SpaceX!$C$37) | H13: =SUM(Microsoft!$C$36,Alphabet!$C$36,Amazon!$C$36,Meta!$C$36,Oracle!$C$36,SpaceX!$C$36)/(SUM(Microsoft!$C$33,Alphabet!$C$33,Amazon!$C$33,Meta!$C$33,Oracle!$C$33,SpaceX!$C$33)+SUM(Microsoft!$C$34,Alphabet!$C$34,Amazon!$C$34,Meta!$C$34,Oracle!$C$34,SpaceX!$C$34))
A14: FY2027 (STREET-EST prediction, static) | E14: -960.45443 | F14: 569.167 | G14: -391.28743 | H14: 0.48899423
A16: SAVINGS BREAKDOWN — the spend cut, split
A17: Cost-weighted reduction (Amdahl) | B17: =Inputs!$B$20 | C17: x
B19: Saved OPEX | C19: Avoided CAPEX (Overspend) | D19: Total
A20: FY2025 annual ($B/yr) | B20: =SUM(Microsoft!B26,Alphabet!B26,Amazon!B26,Meta!B26,Oracle!B26,SpaceX!B26)/1000 | C20: =SUM(Microsoft!B25,Alphabet!B25,Amazon!B25,Meta!B25,Oracle!B25,SpaceX!B25) | D20: =B20+C20
A21: FY2025 capitalized ($B) | B21: =B20/Inputs!$B$6 | C21: =C20/Inputs!$B$6 | D21: =B21+C21
A22: FY2026 annual ($B/yr) | B22: =SUM(Microsoft!C26,Alphabet!C26,Amazon!C26,Meta!C26,Oracle!C26,SpaceX!C26)/1000 | C22: =SUM(Microsoft!C25,Alphabet!C25,Amazon!C25,Meta!C25,Oracle!C25,SpaceX!C25) | D22: =B22+C22
A23: FY2026 capitalized ($B) | B23: =B22/Inputs!$B$6 | C23: =C22/Inputs!$B$6 | D23: =B23+C23
A24: GLOBAL capitalized -- est. ($B) | B24: =D21/Inputs!$B$14 | C24: =D23/Inputs!$B$14 | D24: named-floor capitalized / named-share-of-global (Inputs B14). ESTIMATE: grosses up for other clouds, China, neoclouds, xAI, sovereign.
A25: % reduction | B25: =1-1/Inputs!$B$5 | C25: =1-1/Inputs!$B$20
A26: OPEX = power saved each year (recoupable). CAPEX 'Overspend' = AI capex made unnecessary. TOGGLE: Inputs 'Datacenter scaling factor' (0 = accelerator-only/conservative; 1 = whole datacenter scales with the smaller fleet). At 0 the burn ~halves; at ~0.7 net AI hits breakeven; at 1 it flips positive. Capitalized = annual / discount rate.
A28: TABS
A29: Summary / Value Bridge / Levers | B29: the plain-language front tabs: headline, training vs serving split, where each Helarctos lever moves the needle
A30: Microsoft / Alphabet / Amazon / Meta / Oracle / SpaceX | B30: one tab each: full build capex -> infra -> servers -> accelerator -> fleet/opex -> value
A31: Inputs | B31: global assumptions + the reduction engine (cost-weighted factor)
A32: Sensitivity | B32: SpaceX value across the Today / Ceiling / live cost-weighted tiers + context sensitivity
A33: CostLadder | B33: own-silicon vs buy-NVIDIA vs rent $/GPU-hr
A34: ServingTraining | B34: the serving/training measurement ledger behind the levers — status-tagged (MEASURED / ESTIMATE / TARGET)
A35: Evidence | B35: BOM cost split, accelerator-share data, own-silicon TCO, filing top-lines
A36: Methodology | B36: step-by-step logic, caveats, sources
A38: Legend: yellow = assumption / lever (each maps to a slider in the Streamlit app) · green = disclosed filing or market data · blue = derived formula.

Sheet Inputs
A1: GLOBAL INPUTS — edit yellow (assumption) cells; green = disclosed/market data
A2: Memory reduction factor | B2: 100 | C2: x | D2: 1e-2 memory = 100x less (O(1) internal state vs transformer O(T) KV cache).
A3: FLOPs reduction factor | B3: =$B$24 | C3: x | D3: TODAY scenario (default, RE-BASED 2026-09-01) = x793: the full-workload serving lever (decode 2.5 ms/token x 64 resident streams — an ESTIMATE, aggregate-decode receipt PENDING — prefill at the BANKED x3.936 campaign speedup) x the fit-derived equal-quality parameter ratio x4.22 at 1T (rows 23-25 below). Overtype with =B25 for the CEILING scenario (x816 = same lever, prefill at the full x7.03 maturity factor), or any number. The pre-campaign x9.24 lever is RETIRED 2026-09-01 (measured on kernels that no longer exist). See ServingTraining for the measured background blend.
A4: Memory share of GPU cost (BOM) | B4: 0.6 | C4: frac | D4: HBM ~45% of B200 COGS + most CoWoS packaging -> ~60% memory / ~40% compute. See Evidence.
A5: Opex / energy reduction factor | B5: =B20 | C5: x | D5: DERIVED default = cost-weighted reduction (B20): energy splits memory/compute like cost. Overtype this cell to override.
A6: Discount rate | B6: 0.06 | C6: frac | D6: Perpetuity capitalization: value = annual benefit / rate (=16.7x at 6%).
A7: Fully-loaded cost per GPU | B7: 50000 | C7: $ | D7: B200-class GPU + share of server, NVLink, networking.
A8: Wall power per GPU | B8: 1.8 | C8: kW | D8: ~1 kW TDP + node overhead x PUE 1.3.
A9: Electricity rate | B9: 0.08 | C9: $/kWh | D9: Datacenter wholesale; raise to 0.10-0.12 for grid colo.
A10: Cooling/ops overhead on energy | B10: 0.25 | C10: frac | D10: Non-power running cost as fraction of electricity.
A11: Fleet useful life | B11: 4 | C11: yr | D11: AI-GPU depreciation life.
A12: SpaceX market cap | B12: 1950 | C12: $B | D12: ~$1.95T Aug 2026; IPO 2026-06-12 at ~$1.77T (market data; used by Sensitivity).
A13: Datacenter scaling factor | B13: 0 | C13: frac | D13: TOGGLE 0-1. 0 = conservative (only accelerator silicon shrinks). 1 = whole AI datacenter (building/power/cooling/net) scales with the smaller fleet. ~0.7 ~= breakeven on net AI.
A14: Named share of global AI capex | B14: 0.8 | C14: frac | D14: GLOBAL estimate (Totals): named firms' share of worldwide AI capex; the rest (other clouds, China, neoclouds, xAI, sovereign) is grossed up pro-rata. ESTIMATE.
A15: REDUCTION ENGINE (Amdahl cost-weighting) — derived
A16: Compute share of GPU cost | B16: =1-B4 | D16: 1 - memory share
A17: Memory cost fraction after reduction | B17: =B4/B2 | D17: memory share / memory reduction
A18: Compute cost fraction after reduction | B18: =B16/B3 | D18: compute share / FLOPs reduction
A19: Residual cost fraction | B19: =B17+B18 | D19: Amdahl: floored by the least-reduced component
A20: COST-WEIGHTED reduction factor | B20: =1/B19 | C20: x | D20: 1 / residual. The realistic $ reduction used everywhere.
A22: SCENARIOS (2026-09-01 ruling) — TODAY (default) vs CEILING (campaign landed)
A23: Equal-quality parameter ratio at 1T | B23: 4.2185 | C23: x | D23: FIT-DERIVED (sealed 2026-08-14 refit): bAttention matches the transformer fit's quality on 23.7% of the params at 1T -> x4.22 compute per token at equal quality. 84.2% at 1B, 55.2% at 10B, 36.2% at 100B, 15.5% at 10T (x6.44). A projection of the two fits, not a measurement.
A24: TODAY compute lever = serving lever x ratio | B24: =188.0305*$B$23 | C24: x | D24: B3 (the FLOPs lever) points here by default. The x188.0 serving half is model-computed (campaign_landed_flop_lever): decode 2.5 ms/token x 64 resident streams — an ESTIMATE, the aggregate-decode receipt is PENDING — with prefill at the BANKED x3.936 (our own step went 400.4 -> 101.7 ms at B16/T2048; 2026-08-29 clean-wall position of record); transformer side stays the measured 1/context law at its KV ceiling, 128k E[context].
A25: CEILING compute lever (campaign landed) | B25: =193.3376*$B$23 | C25: x | D25: Same full-workload lever with prefill at the full x7.03 maturity factor = x3.936 MEASURED (already banked) x x1.786 TARGET (the funded 8k-win gate, no receipt yet). Decode-dominated, so it sits only ~3% above TODAY. Overtype B3 with =B25 to run the workbook at the ceiling (~x154 cost-weighted — memory-floored; dollars move within rounding).

Sheet Sensitivity
A1: SENSITIVITY (SpaceX) — TODAY vs CEILING vs live cost-weighted
A2: Metric | B2: TODAY (~154x) | C2: CEILING (~154x) | D2: Cost-weighted (live)
A3: Efficient acquisition ($B) | B3: =SpaceX!$B$12/(1/(Inputs!$B$4/Inputs!$B$2+(1-Inputs!$B$4)/Inputs!$B$24)) | C3: =SpaceX!$B$12/(1/(Inputs!$B$4/Inputs!$B$2+(1-Inputs!$B$4)/Inputs!$B$25)) | D3: =SpaceX!$B$12/(Inputs!$B$20)
A4: Capex avoided/yr ($B) | B4: =SpaceX!$B$12-SpaceX!$B$12/(1/(Inputs!$B$4/Inputs!$B$2+(1-Inputs!$B$4)/Inputs!$B$24)) | C4: =SpaceX!$B$12-SpaceX!$B$12/(1/(Inputs!$B$4/Inputs!$B$2+(1-Inputs!$B$4)/Inputs!$B$25)) | D4: =SpaceX!$B$12-SpaceX!$B$12/(Inputs!$B$20)
A5: Annual opex savings ($M) | B5: =SpaceX!$B$26 | C5: =SpaceX!$B$26 | D5: =SpaceX!$B$26
A6: Sustained annual benefit ($B) | B6: =(SpaceX!$B$12-SpaceX!$B$12/(1/(Inputs!$B$4/Inputs!$B$2+(1-Inputs!$B$4)/Inputs!$B$24)))+SpaceX!$B$26/1000 | C6: =(SpaceX!$B$12-SpaceX!$B$12/(1/(Inputs!$B$4/Inputs!$B$2+(1-Inputs!$B$4)/Inputs!$B$25)))+SpaceX!$B$26/1000 | D6: =(SpaceX!$B$12-SpaceX!$B$12/(Inputs!$B$20))+SpaceX!$B$26/1000
A7: Capitalized value ($B) | B7: =((SpaceX!$B$12-SpaceX!$B$12/(1/(Inputs!$B$4/Inputs!$B$2+(1-Inputs!$B$4)/Inputs!$B$24)))+SpaceX!$B$26/1000)/Inputs!$B$6 | C7: =((SpaceX!$B$12-SpaceX!$B$12/(1/(Inputs!$B$4/Inputs!$B$2+(1-Inputs!$B$4)/Inputs!$B$25)))+SpaceX!$B$26/1000)/Inputs!$B$6 | D7: =((SpaceX!$B$12-SpaceX!$B$12/(Inputs!$B$20))+SpaceX!$B$26/1000)/Inputs!$B$6
A8: % of market cap | B8: =(((SpaceX!$B$12-SpaceX!$B$12/(1/(Inputs!$B$4/Inputs!$B$2+(1-Inputs!$B$4)/Inputs!$B$24)))+SpaceX!$B$26/1000)/Inputs!$B$6)/Inputs!$B$12 | C8: =(((SpaceX!$B$12-SpaceX!$B$12/(1/(Inputs!$B$4/Inputs!$B$2+(1-Inputs!$B$4)/Inputs!$B$25)))+SpaceX!$B$26/1000)/Inputs!$B$6)/Inputs!$B$12 | D8: =(((SpaceX!$B$12-SpaceX!$B$12/(Inputs!$B$20))+SpaceX!$B$26/1000)/Inputs!$B$6)/Inputs!$B$12
A10: Base = SpaceX accelerator capex (SpaceX!B12), not total capex. The 'Cost-weighted' column ties to the SpaceX tab (B25/B27) at the conservative dc_scale=0.
A12: CONTEXT SENSITIVITY — prefill share of serving cost vs fleet E[context]
A13: E[context] | B13: TF prefill share | C13: Our prefill share (Today) | D13: Today lever (x) | E13: Ceiling lever (x) | F13: Today->Ceiling gap
A14: 8k | B14: 0.0058992503 | C14: 0.052089954 | D14: 50.296652 | E14: 51.477062 | F14: 0.023468945
A15: 32k | B15: 0.002981161 | C15: 0.051966315 | D15: 200.62394 | E15: 205.32093 | F15: 0.023411936
A16: 128k (pinned) | B16: 0.0023592668 | C16: 0.062355756 | D16: 793.20649 | E16: 815.59451 | F16: 0.028224711
A17: 256k | B17: 0.0023005044 | C17: 0.082213812 | D17: 1552.7234 | E17: 1611.0294 | F17: 0.037550789
A19: Cost = box wall-clock, not FLOPs. The transformer's decode leg is KV-bandwidth-bound (measured 1/context law) while its prefill runs near peak, so prefill is <1% of its serving cost at every context — which is why the banked x3.936 prefill (TODAY) and the full x7.03 (CEILING) land within a few percent of each other. Inputs!B24/B25 quote the pinned 128k row (2026-08-31 fleet-context ruling). Static values from the the model — rebuild the workbook to refresh.

Sheet CostLadder
A1: COST LADDER — $/H100-equivalent GPU-hour (at scale). Green = market price; yellow = assumption.
A2: Procurement mode | B2: $/hr low | C2: $/hr high | D2: What's baked into the price
A3: Own custom silicon (TPU/Trainium) | B3: 0.9 | C3: 1.4 | D3: COGS + modest Broadcom/Marvell margin + power + DC. NO NVIDIA margin.
A4: Buy + operate NVIDIA (scale) | B4: 1.5 | C4: 2 | D4: NVIDIA ~84% gross margin baked into capex + power + DC.
A5: Rent NVIDIA - neocloud / committed | B5: 2 | C5: 3.5 | D5: + cloud provider capex recovery & margin.
A6: Rent NVIDIA - hyperscaler on-demand | B6: 3 | C6: 7 | D6: + utilization risk + flexibility premium (new B200 to ~$14).
A8: OWNED-NVIDIA TCO CROSS-CHECK (from Inputs)
A9: Utilization | B9: 0.85
A10: Capex $/hr | B10: =Inputs!$B$7/(Inputs!$B$11*8760*B9) | D10: fully-loaded $/GPU / (life x 8760h x utilization)
A11: Power $/hr | B11: =Inputs!$B$8*Inputs!$B$9 | D11: wall kW x $/kWh
A12: DC/staff adder $/hr | B12: 0.3
A13: Owned TCO $/hr | B13: =B10+B11+B12 | D13: cross-checks the 'Buy + operate NVIDIA' row
A15: MARGIN STACK: own-silicon -> buy-NVIDIA ~1.4-2x (NVIDIA margin). buy -> rent ~2-3.5x (cloud margin). own -> rent ~3-5x.
A16: B200 builds ~$6,400, sells ~$40,000 -> ~84% gross margin. Hyperscalers charge 3-6x neocloud rates for identical HW.
A17: OWN-SILICON: TPU/Trainium/MTIA cost ~1/3 less per useful FLOP than NVIDIA. The model values compute at each company's ACTUAL cost (no gross-up).
A18: SemiAnalysis: TPU 20-50% lower TCO per useful FLOP vs GB200/GB300; Trainium3 ~30% better vs GB300.
A19: Sources: Spheron/IntuitionLabs (rental), Silicon Analysts (B200 cost/margin), SemiAnalysis (TPU/Trainium TCO).

Sheet ServingTraining
A1: SERVING & TRAINING — measured 2026-08-07/08 (2/4/8 x H100), priced at the CostLadder rent mid ($2.50/GPU-hr). Source: internal measurement archive (keys in the model).
A4: WORKLOAD — measured pre-campaign blend (background; the workbook lever lives at Inputs B24/B25)
A5: Training, prefill and decode point in opposite directions at today's kernel maturity, so the compute lever is blended over the workload rather than fixed. Cost per GENERATED token = in:out input tokens through prefill + one token through decode. Transformer decode follows the MEASURED 1/context law at its own KV ceiling (granted no KV compression by default; raise the KV-compression cell below to grant it a mature stack).
A7: Input : output token ratio | B7: 10 | F7: ~10:1 = code / reasoning / agent traces. 50-100:1 = RAG and document QA.
A8: E[context] (tokens) | B8: 65536 | F8: Our decode cost is context-flat and the transformer's is linear, so the decode advantage is linear in this.
A9: Training share of accelerator cost | B9: 0 | F9: 0 = a serving-cost claim. Training is a LOSS at short sequence today; above ~0.06 the blend drops below 1.
A11: Measured constants
A12: Owned decode, tokens/s/box (context-flat) | B12: 4496.6686
A13: KV MB per token per stream | B13: 0.15234375
A14: HBM TB/s per GPU | B14: 3.35
A15: Transformer KV compression (mature stack) | B15: 1
A16: GPUs per box | B16: 8
A17: Training advantage, short sequence (owned / transformer) | B17: 0.58256092 | F17: RE-BASED 2026-08-24/25 (1 x GH200, ONE layer, fwd+bwd, bf16, checkpointing off both arms, modern transformer block 24Q/4KV head_dim 256 RoPE 64 gated): transformer is 1.72x faster at T=2,048 (101.7 vs 59.3 ms/step) and 1.79x at T=8,192; the equal-token B4/T32,768 ~parity cell is RETIRED 2026-08-25 as a B4 occupancy artifact, and the flat per-token model puts the crossover at a PROJECTED T~13,008 (from T~88,000 pre-campaign). It read 6.12x (400.4 ms) the same morning. Training PEAK MEMORY, same frame: 1.579x at T=2,048 (17,087.5 vs 10,823.6 MiB), from 2.829x -- that is TRAINING memory, not the /100 SERVING lever. TARGET (no receipt): T=8,192 step <= 83.08 ms and memory 0.88x.
A19: Derived
A20: KV GB per stream | B20: =$B$8*$B$13/1024
A21: KV GB per stream, compressed | B21: =$B$20/$B$15
A22: Transformer decode, tokens/s/box | B22: =511.8416*32768/$B$8*$B$15*$B$16 | F22: MEASURED 1/context law (2026-08-14 re-base): 511.84 tok/s/GPU at 32,768 ctx x 32768/E[context] x KV-compression x GPUs. Crosses our flat 562/GPU near ~30k context.
A23: Prefill table row (lookup) | B23: =MATCH($B$8,$A$33:$A$39,1)
A24: Prefill tokens/s/box — transformer | B24: =IF(INDEX($B$33:$B$39,MIN($B$23+1,7))=INDEX($B$33:$B$39,$B$23),INDEX($B$33:$B$39,$B$23),EXP(LN(INDEX($B$33:$B$39,$B$23))+(LN($B$8)-LN(INDEX($A$33:$A$39,$B$23)))/(LN(INDEX($A$33:$A$39,MIN($B$23+1,7)))-LN(INDEX($A$33:$A$39,$B$23)))*(LN(INDEX($B$33:$B$39,MIN($B$23+1,7)))-LN(INDEX($B$33:$B$39,$B$23)))))*$B$16
A25: Prefill tokens/s/box — owned | B25: =IF(INDEX($C$33:$C$39,MIN($B$23+1,7))=INDEX($C$33:$C$39,$B$23),INDEX($C$33:$C$39,$B$23),EXP(LN(INDEX($C$33:$C$39,$B$23))+(LN($B$8)-LN(INDEX($A$33:$A$39,$B$23)))/(LN(INDEX($A$33:$A$39,MIN($B$23+1,7)))-LN(INDEX($A$33:$A$39,$B$23)))*(LN(INDEX($C$33:$C$39,MIN($B$23+1,7)))-LN(INDEX($C$33:$C$39,$B$23)))))*$B$16
A26: Transformer seconds per generated token | B26: =$B$7/$B$24+1/$B$22
A27: Owned seconds per generated token | B27: =$B$7/$B$25+1/$B$12
A28: BLENDED COMPUTE LEVER (flop_factor) | B28: =IF($B$9>0,1/($B$9/$B$17+(1-$B$9)/($B$26/$B$27)),$B$26/$B$27) | F28: Measured pre-campaign workload blend (2026-08-14 basis), kept as BACKGROUND. RETIRED as the workbook lever 2026-09-01: Inputs!B24/B25 now carry the model-computed full-workload levers (decode 2.5 ms x 64 streams estimate; this cell no longer feeds Inputs!B3).
A29: of which: prefill advantage | B29: =($B$7/$B$24)/($B$7/$B$25)
A30: of which: decode advantage | B30: =(1/$B$22)/(1/$B$12)
A32: Measured prefill throughput, tokens/s/GPU (bf16 saturated lane, d2048) | D32: Context | E32: Transformer | F32: Owned
A33: 2048 | B33: 4682606.9 | C33: 1185825
A34: 8192 | B34: 3450080 | C34: 1183690
A35: 32768 | B35: 1711802 | C35: 1186661
A36: 65536 | B36: 1007187 | C36: 1181622
A37: 131072 | B37: 541094 | C37: 978107
A38: 262144 | B38: 277474 | C38: 726142
A39: 524288 | B39: 140820 | C39: 478522
A41: SCOPE: the serving and training blocks below are component-scope systems benches (bAttention d1536 fwd+bwd h-internal dynamics sub-block vs transformer d2048 forward-only layer); every speedup there is each family vs its OWN 1-GPU baseline. The prefill lanes quoted further down are cross-family: 16-bit parameter-matched at block scope (the fp32 full-model sweep is retired to an assumption row).
A43: Serving at long context — $/1M generated tokens, one 8xH100 box
A44: Context (tokens) | B44: bAttention $/1M tok | C44: Transformer $/1M tok (mature stack) | D44: TF streams/GPU | E44: Cost ratio | F44: Note
A45: 4096 | B45: 1.2354825 | C45: 0.16959456 | D45: 118 | E45: 0.1372699
A46: 16384 | B46: 1.2354825 | C46: 0.67837826 | D46: 29 | E46: 0.5490796
A47: 32768 | B47: 1.2354825 | C47: 1.3567565 | D47: 14 | E47: 1.0981592
A48: 65536 | B48: 1.2354825 | C48: 2.713513 | D48: 7 | E48: 2.1963184
A49: 131072 | B49: 1.2354825 | C49: 5.427026 | D49: 3 | E49: 4.3926368
A50: 262144 | B50: 1.2354825 | C50: 10.854052 | D50: 1 | E50: 8.7852736 | F50: a measured decode cell (64 streams/GPU against the transformer 1)
A51: 1048576 | B51: 1.2354825 | D51: 0 | F51: bAttention rate extrapolated past 262k (flatness measured 4k-262k)
A52: RE-BASED 2026-08-14 on the full-model decode receipt: per-GPU aggregate throughput at each family's own concurrency ceiling, transformer granted no KV compression. Ratio ~ context/29,800, so the TRANSFORMER is ahead below ~30k context; x2.2 at 64k, x8.8 at 262k. Memory-ceiling result, not a per-token one - at one stream and 64k the transformer decodes a token faster than we do. Granting it KV /8: x1.1 at 262k.
A54: Training at scale — same cluster, more steps/s
A55: Metric | B55: Value | C55: Ratio / consequence | F55: Status — internal measurement archive key
A56: 8-GPU speedup, matched load (16 in flight) | B56: x5.15 fwd+bwd vs x3.70 fwd-only Ulysses best | C56: x1.39 cluster throughput | F56: MEASURED — matched_load_curve
A57: 8-GPU speedup, deep load (256 in flight) | B57: x6.27 (pipeline keeps filling; TF saturated by 16) | C57: x1.70 | F57: MEASURED — scaling_1to8_best
A58: GPU-hours for the same training work | B58: -28% (matched) … -41% (deep) | F58: derived
A59: 64k-token sequence on one 80 GB GPU | B59: 30.9 GB fits vs OOM (78.4 GB attempted) | F59: MEASURED — pipeline_feasibility
A60: Pipeline per-GPU peak (flat in load) | B60: 9.05 GB vs 43.3 GB GPipe stage | C60: x4.8 (component-scope, width-unmatched) | F60: MEASURED — pipeline_memory_asymmetry
A61: Params for equal quality at 70B | B61: x4.1 [2.2-7.7] transformer | F61: PROJECTION — quality_fit.ref_70B
A62: Tokens for equal quality at 70B | B62: x1.68 [1.33-2.10] (beta=0.28 assumption) | F62: PROJECTION — quality_fit.ref_70B
A63: Token-by-token vs production training | B63: x24 cost to run training token-by-token instead of the production path | F63: MEASURED — token-by-token ratio
A65: The measured workload blend (pre-campaign background; the workbook lever lives at Inputs B24/B25)
A66: Training, prefill and decode point in OPPOSITE directions at today's kernel maturity, so a single number cannot represent them. Training is still a loss at short sequence, but a much smaller one since the 2026-08-24 kernel re-base (transformer 1.72x faster at T=2,048 and 1.79x at T=8,192, crossover near T~13,000 (2026-08-29 anchor); it was 5.3-9.6x with a crossover near T~88,000 on the pre-campaign d1152 sweep). Prefill crosses over near 65k context. Decode crosses in our favour near ~30k context. The lever is therefore blended over the workload: per generated token, in:out input tokens through prefill plus one token through decode, using measured per-GPU throughput at each family's own concurrency ceiling, the transformer granted no KV compression. At the default operating point (10:1, 64k context, training share 0): prefill x1.17, decode x2.20, blended x2.19, with decode ~99.7% of transformer serving cost. The decode half is a MEMORY CEILING, not a per-token result - at one stream and 64k the transformer decodes a token more cheaply than we do - and it crosses 1 at ~30k context, below which the transformer wins. Granting it KV/8 divides our decode lever by 8. A training share above ~0.30 also takes the blend below 1 (it was ~0.06 before the kernel re-base). All are reachable in the live model. NOTE (2026-09-01): this blend was measured on the PRE-CAMPAIGN kernels and no longer sets the workbook's flop_factor — the scenario levers at Inputs B24/B25 fold in the banked kernel results and the aggregate-decode estimate.
A68: Estimated TRAINING cost at equal quality (ESTIMATE: measured kernels x fitted quality)
A69: Training compute ~ 6*N*D FLOPs. At equal quality we need N/s parameters, where s(N) is the FIT-DERIVED equal-quality parameter ratio (the same sealed 2026-08-14 refit as the compute lever). Two token regimes differ by exactly one power of s: COMPUTE-OPTIMAL (Chinchilla, D proportional to N -> cost ratio s^2/r) and FIXED TOKEN BUDGET (D equal on both arms -> s/r). r(T) is the step-time ratio at matched parameters: MEASURED at T=2,048 (1.72x, 2026-08-25) and T=8,192 (1.79x, 2026-08-24), MODELED beyond. Above 1.00 we are cheaper to train to the same quality. The 256k column is MODELED from the per-token cost form -- the transformer pays base + attn*T per token (FlashAttention is linear per token), our O(1) internal state pays ~flat -- with base and attn fitted to the 2k and 8k cells ONLY. The fit is flat -- the +5.8%-per-4x residual and the B4/T32,768 ~parity cell that shared it are RETIRED 2026-08-25 as a B4 occupancy artifact -- and puts the crossover at a PROJECTED T~13,008. The old constant-decay extrapolation (0.758 per 4x) is kept as the CONSERVATIVE bound and reads 0.65 at 256k against this form's 0.10. The fits cross at 392M, so below that we need MORE parameters, and every row past ~1B extrapolates beyond the measured 47M-663M rungs. Peak training memory (1.58x measured, 0.88x targeted) is NOT in this model: it caps per-GPU batch density, not FLOPs. Chart: internal measurement archive
A71: Transformer params | B71: s(N) fit | C71: Chinchilla 2k | D71: Chinchilla 8k | E71: Chinchilla 32k | F71: Chinchilla 256k* | G71: Fixed-D 2k / 8k / 32k / 256k*
A72: 1B | B72: 1.1875366 | C72: 0.82155253 | D72: 1.1515708 | E72: 2.4716439 | F72: 14.792326 | G72: 0.69 / 0.97 / 2.08 / 12.46
A73: 10B | B73: 1.8119686 | C73: 1.9126815 | D73: 2.6810071 | E73: 5.7543094 | F73: 34.438465 | G73: 1.06 / 1.48 / 3.18 / 19.01
A74: 100B | B74: 2.7647401 | C74: 4.4529721 | D74: 6.2417343 | E74: 13.396783 | F74: 80.17724 | G74: 1.61 / 2.26 / 4.85 / 29.00
A75: 1T | B75: 4.2184992 | C75: 10.3671 | D75: 14.531572 | E75: 31.18946 | F75: 186.66308 | G75: 2.46 / 3.44 / 7.39 / 44.25
A76: 10T | B76: 6.4366758 | C76: 24.135962 | D76: 33.831396 | E76: 72.613132 | F76: 434.576 | G76: 3.75 / 5.26 / 11.28 / 67.52
A78: TRAINING IS A CURRICULUM, NOT ONE CONTEXT. Quoting r at a single T assumes ALL training happens there; this model used to assume T=2,048 for all of it, which is the pessimistic corner. The correct training term is the ratio of COSTS integrated over the mix of contexts a run actually uses, NOT the average of the per-context ratios. That distinction does the work: our per-token cost is flat in context and the transformer's grows, so long-context tokens dominate its bill while staying a token minority. TOKEN SHARES BELOW ARE ILLUSTRATIVE KNOBS -- this repo carries no citation for any lab's training recipe and none is invented here; only the first row (the degenerate one-context case) is anchored to a measurement. Effective r crosses below 1 at every modern mix, but RAISING the dollar headline is a higher bar: the blended lever is a cost-weighted harmonic mean, so training only pushes the headline up once it beats the SERVING advantage of 2.19x, not merely 1.00x. Between the two it is profitable and still dilutive.
A80: Training curriculum | B80: Advantage (TF / ours) | C80: Effective r | D80: Mix: token share -> transformer cost share | E80: FY25 cut @ 20% training | F80: vs serving-only | G80: Status
A81: Legacy short (all training at 2k) | B81: 0.58256092 | C81: 1.7165587 | D81: 2k: 100% tok -> 100% cost | E81: 149.77738 | F81: -10.772828 | G81: MEASURED (degenerate one-context case)
A82: Modern standard (8k bulk + 64k/256k extension) | B82: 2.220667 | C82: 0.45031515 | D82: 8k: 70% tok -> 26% cost 64k: 20% tok -> 27% cost 256k: 10% tok -> 47% cost | E82: 153.65794 | F82: -6.89227 | G82: ILLUSTRATIVE ASSUMPTION
A83: Long-context heavy (frontier extension phases) | B83: 7.7434247 | C83: 0.12914183 | D83: 8k: 40% tok -> 4% cost 64k: 25% tok -> 10% cost 256k: 25% tok -> 34% cost 1024k: 10% tok -> 52% cost | E83: 154.64222 | F83: -5.9079952 | G83: ILLUSTRATIVE ASSUMPTION
A84: Frontier + long-rollout RL | B84: 12.080506 | C84: 0.082777992 | D84: 8k: 30% tok -> 2% cost 64k: 20% tok -> 5% cost 256k: 30% tok -> 26% cost 1024k: 20% tok -> 67% cost | E84: 154.78431 | F84: -5.7659075 | G84: ILLUSTRATIVE ASSUMPTION
A86: EXCLUDED, AND IT RUNS OUR WAY. At 262k+ the transformer additionally pays sequence-parallelism and activation-memory costs an O(1) internal state avoids: its KV grows at 156 KB per token of context per stream, which is what forces sharding, ring/Ulysses attention and their communication overhead. Our own measurement shows the asymmetry in the small -- from 2k to 8k the peak-memory ratio went 1.579x -> 1.567x, i.e. flat-to-falling in context, while the absolute footprint the transformer must shard keeps growing. None of it is in the cost model above, which counts step time only, so the omission is CONSERVATIVE. Quantifying it needs a multi-GPU long-context TRAINING receipt we do not have.
A88: The prefill component, 16-bit and parameter-matched — the lane the competition serves in. Parameter counts exactly matched, 1 layer, batch 16, 1 x H100 80GB HBM3, 2026-07-21 — x4.02 at d512/1M, x3.83 at d1024/1M, x2.01 at d2048/262k. The fp32 full-model sweep and the own-baseline 16-bit-IO training gate are retired to one assumption row each below. Receipts: internal measurement archive{512,1024,2048}internal measurement archive
A90: Context (tokens) | B90: Transformer ms | C90: bAttention ms | D90: TF / bAttention | F90: Note
A91: 2048 | B91: 111.229 | C91: 663.113 | D91: 0.16773763 | F91: transformer ahead
A92: 4096 | B92: 125.091 | C92: 662.751 | D92: 0.18874509 | F92: transformer ahead
A93: 8192 | B93: 153.085 | C93: 663.327 | D93: 0.23078361 | F93: transformer ahead
A94: 16384 | B94: 204.919 | C94: 663.202 | D94: 0.30898429 | F94: transformer ahead
A95: 32768 | B95: 309.886 | C95: 662.618 | D95: 0.46766915 | F95: transformer ahead
A96: 65536 | B96: 520.986 | C96: 663.199 | D96: 0.78556512 | F96: transformer ahead
A97: 131072 | B97: 969.79 | C97: 753.457 | D97: 1.2871206
A98: 262144 | B98: 1889.616 | C98: 938.175 | D98: 2.0141402
A99: 524288 | B99: 3718.717 | C99: 1308.837 | D99: 2.8412377
A101: Assumptions — one row each (MEASURED / PROJECTION / ASSUMPTION)
A102: Assumption | B102: Value | E102: Status | F102: Source
A103: Compute lever (Today, 2026-09-01 re-base) | B103: x793 = full-workload serving lever (decode 2.5 ms/token x 64 streams ESTIMATE, prefill at the BANKED x3.94) x the x4.22 FIT-DERIVED equal-quality ratio at trillion scale; Ceiling = same at the full x7.03 maturity factor (x816) | E103: ESTIMATE x PROJECTION | F103: the model; aggregate-decode receipt PENDING (internal measurement archive)
A104: Equal-quality parameter matching | B104: sealed 2026-08-14 refit, 4 rungs per family (47M-663M params): the fits cross at 392M and bAttention then matches the transformer fit's quality on 84.2% of the params at 1B, 55.2% at 10B, 36.2% at 100B, 23.7% at 1T, 15.5% at 10T. The receipt's own words: 'a projection of the two fits, not a measurement' | E104: PROJECTION | F104: internal measurement archive param_matching; fits over the sealed rope-convention ladder
A105: Single-GPU training step (AGAINST us) | B105: RE-BASED 2026-08-24: on one GH200, single layer, fwd+bwd, bf16, checkpointing off both arms, against a MODERN transformer block (24Q/4KV, head_dim 256, RoPE 64, gated attention), a bAttention step costs x1.72 MORE at T=2,048 (101.7 vs 59.3 ms/step) and x1.79 at T=8,192. It read x6.116 (400.4 ms) the same morning and x6.46 on the older d1536/27L fp16 601-step receipt. Fwd x1.82, bwd x2.35. Training is still excluded from the serving claim, but the gap is now a kernel-program line item with a funded gate, not a structural loss | E105: MEASURED | F105: 2026-08-24 GH200 megakernel measurement; prior: internal measurement archive rows[fp16]
A106: Training PEAK MEMORY (AGAINST us) | B106: x1.579 at T=2,048 (17,087.5 vs 10,823.6 MiB) and x1.567 at T=8,192, down from x2.829 the same morning. This is TRAINING peak memory and is NOT the mem_factor lever, which is SERVING state (O(1) internal state vs O(T) KV cache) and is unaffected. It is not an input to the cost model; it caps per-GPU batch density | E106: MEASURED | F106: 2026-08-24 GH200 megakernel measurement
A107: Kernel program (TARGET, not a result) | B107: the funded 8k-win gate is a T=8,192 step at or below 83.08 ms, i.e. x1.786 still to remove (44% of the step). Named levers: recompute removal ~-12.8 ms; backward-fold + occupancy redesign (~3x headroom in the dominant fused kernel); copies elimination (24.8% of the step). Memory target x0.88 (parity or below). the model = the MEASURED x3.936 already banked x this x1.786 target | E107: TARGET | F107: kernel-campaign program plan, 2026-08-24 — no receipt behind the target half
A108: Context scaling of the training gap | B108: at matched tokens/step, 2k -> 8k (4x context): our step grows x1.000, the transformer's x1.319, so the ratio decays x0.758 per 4x. The equal-token B4/T32,768 ~parity cell is RETIRED 2026-08-25 as a B4 occupancy artifact (it shared the retired growth residual); the flat per-token model puts the crossover at a PROJECTED T~13,000 (the model, 2026-08-29 anchor). Holding the old x0.802 decay constant instead would say x1.43 at 32k and a crossover near T~310,000 - that is the CONSERVATIVE extrapolation, because the transformer's quadratic attention term makes its per-4x growth rise with context while ours stays flat | E108: MEASURED (2 ratio points) + PROJECTION | F108: 2026-08-24 GH200 megakernel measurement; 2k cell re-based 2026-08-25
A109: Training CONTEXT MIX (reads the other way) | B109: quoting one context for all of training is the pessimistic corner, and it was this model's old implicit assumption. Cost-weighted over a curriculum the training term flips from a DRAG to a CONTRIBUTOR: x0.583 at 100% 2k, x2.22 at a modern 8k/64k/256k mix, x7.74 long-context-heavy, x12.08 with long RL rollouts. The mechanism: our per-token cost is FLAT in context and the transformer's GROWS, so long-context tokens dominate its bill as a token minority — 10% of tokens at 262k is 47% of its training cost. r(T) is MEASURED at 2k/8k and MODELED beyond; the curriculum SHARES are ILLUSTRATIVE and exposed as knobs (this repo carries no citation for any lab's recipe) | E109: MEASURED r(T) + ILLUSTRATIVE mix | F109: the model, the model, the model
A110: Long-context training memory (EXCLUDED, runs our way) | B110: at 262k+ the transformer additionally pays sequence-parallelism and activation-memory costs that an O(1) internal state does not: its KV grows at 156 KB per token of context per stream, which is what forces sharding, ring/Ulysses attention and their communication overhead. Our own measurement shows the asymmetry in the small: peak training memory grew only x0.993 relative to the transformer's from 2k to 8k (x1.579 -> x1.567), i.e. the ratio is FLAT-to-falling in context while the absolute gap the transformer must shard grows. NOT in the cost model — the training advantage above counts FLOPs/step-time only, so the direction of this omission is CONSERVATIVE (it understates us at long context). Quantifying it needs a multi-GPU long-context training receipt we do not have | E110: DIRECTIONAL — measured components, not a costed lever | F110: the model mem_ratio_2k/8k; the model
A111: $/GPU-hour | B111: $2.50 (H100 rent, neocloud/committed mid; ladder 2.00-3.50) | E111: ASSUMPTION | F111: this file's CostLadder row — unchanged rate basis
A112: Utilization | B112: 85% | E112: ASSUMPTION | F112: same value as the ladder's owned-TCO cross-check
A113: Context-length mix | B113: headline quoted at 262k (a measured decode cell); table sweeps 4k-1M. The decode lever crosses 1 at ~29,800 tokens and BELOW that the transformer serves more tokens per GPU-second than we do — stated on every surface | E113: ASSUMPTION | F113: serving_cost_curve, decode_throughput_ratio
... A125: Scope | B125: systems numbers are component-scope (bAttention d1536 fwd+bwd h-internal dynamics sub-block vs transformer d2048 forward-only layer); every speedup is vs the family's OWN 1-GPU baseline | E125: LABEL | F125: internal measurement archive scope_reconciliation; deck README

Sheet Evidence
A1: EVIDENCE — cost split, accelerator share, own-silicon TCO, filing data
A3: GPU cost split (BOM) | B3: $ cost | C3: % COGS | D3: Method 1: teardown = true resource cost
A4: H100: HBM3 memory (80GB) | B4: 1350 | C4: 41% | D4: MEMORY
A5: H100: CoWoS packaging | B5: 750 | C5: 23% | D5: mostly memory (interposer hosts HBM)
A6: H100: test & assembly | B6: 920 | C6: 28% | D6: shared
A7: H100: logic die (compute) | B7: 300 | C7: 9% | D7: COMPUTE -- cheapest part
A8: H100 total COGS | B8: 3320 | C8: 100% | D8: sells ~$28k -> ~88% margin
A9: B200 total COGS | B9: 6400 | C9: HBM 45% | D9: memory > logic die; sells ~$40k -> ~84% margin
A11: Accelerator share of server BOM | D11: for accel-within-server share
A12: 8x H100 server (J.P. Morgan) | B12: 83% | D12: accelerator = $200k of $240k
A13: 8x A100 server (J.P. Morgan) | B13: 71% | D13: GB200 rack ~76-80% (SemiAnalysis)
A15: Own-silicon vs NVIDIA (TCO) | D15: cheaper, but valued at cost in model
A16: Google TPU v7 vs GB200/GB300 | B16: 20-50% lower | D16: per useful FLOP (SemiAnalysis)
A17: Amazon Trainium3 vs GB300 | B17: ~30% better | D17: chips ~1/3 cheaper to build
A19: Filing data (FY2025 actuals) | B19: total capex | C19: server life | D19: DISCLOSED top-lines
A20: Microsoft (Jun'25, incl leases) | B20: ~$88B | C20: 2-6 yr | D20: 'roughly half' short-lived (CFO)
A21: Alphabet | B21: $91.4B | C21: 6 yr | D21: 60% servers / 40% DC (CFO)
A22: Amazon (cash capex) | B22: $128.3B | C22: 5 yr (cut) | D22: AWS 67.8% of net P&E additions
A23: Meta (incl finance leases) | B23: $72.2B | C23: 5.5 yr | D23: servers 'largest portion' (CFO)
A24: FY26 capex guidance | D24: MSFT ~$190B, Alphabet $180-190B, Amazon ~$200B, Meta $125-145B, Oracle ~$50B; SpaceX ~$18B (est)
A26: Cost-weighted reduction vs memory share | B26: reduction (x) | D26: live: =1/(w/memfac+(1-w)/flopfac)
A27: memory share = 45% | B27: 0.45 | C27: =1/(B27/Inputs!$B$2+(1-B27)/Inputs!$B$3) | D27: memory term dominates -> pinned near the 100x memory lever
A28: memory share = 50% | B28: 0.5 | C28: =1/(B28/Inputs!$B$2+(1-B28)/Inputs!$B$3) | D28: memory term dominates -> pinned near the 100x memory lever
A29: memory share = 60% | B29: 0.6 | C29: =1/(B29/Inputs!$B$2+(1-B29)/Inputs!$B$3) | D29: memory term dominates -> pinned near the 100x memory lever
A30: memory share = 70% | B30: 0.7 | C30: =1/(B30/Inputs!$B$2+(1-B30)/Inputs!$B$3) | D30: memory term dominates -> pinned near the 100x memory lever
A31: memory share = 82% | B31: 0.82 | C31: =1/(B31/Inputs!$B$2+(1-B31)/Inputs!$B$3) | D31: memory term dominates -> pinned near the 100x memory lever

Sheet Methodology
A1: METHODOLOGY & SOURCES
A3: Engine: GPU cost ~60% memory / ~40% compute. RE-BASED 2026-09-01: TODAY (default): memory x100 + FLOPs x793 (full-workload serving lever — decode 2.5 ms/token x 64 streams ESTIMATE, prefill at the banked x3.936 — x equal-quality ratio x4.22 at 1T) -> ~x154 cost-weighted (Inputs B20). CEILING: FLOPs x816 (prefill at the full x7.03 maturity factor = x3.936 measured x x1.786 target) -> ~x154.
A4: Floored by the least-reduced part — at these levers that is MEMORY (/100), so the two scenarios land within rounding of each other. The pre-campaign family (x9.24 -> ~20x / x28.2 -> ~50x) is RETIRED 2026-09-01: measured on kernels that no longer exist.
A6: Per company (own tab): total capex (DISCLOSED) x infra share x server share x accelerator share = accelerator capex; then fleet -> opex -> efficient -> value. FY25 + FY26.
A7: infra (data-center) share from 10-K/10-Q P&E and segment notes (MSFT 97%, Alphabet 93-95%, Meta 95-98%, Amazon AWS 68-76%); server share CFO-disclosed (MSFT ~50%, Google 60%); accel-within-server ~67-80% from BOM.
A8: Accel % of total varies: Amazon ~30% (legacy fleet + non-AI), MSFT ~37%, Google ~40%, Meta ~48%, SpaceX ~79% (greenfield).
A9: Totals (front page): rolls up the company tabs live; no double-count (they don't pay each other for the bulk). GLOBAL row grosses the named total up to a worldwide estimate (Inputs 'Named share of global AI capex').
A10: Value: spend cut/yr = accel x (1 - 1/reduction) ~95% + opex savings; capitalized = annual / discount rate. Compute valued at ACTUAL cost.
A11: Energy/opex reduction: DERIVED = cost-weighted reduction (energy splits memory/compute like cost). Inputs B5 defaults to =B20; overtype that cell to override.
A12: HOW EACH INPUT IS DERIVED: Inputs sheet column D notes every global assumption; Evidence sheet has the BOM cost split (mem share), accelerator-share teardowns, own-silicon TCO and filing top-lines; per-company capex/shares/revenue carry a basis + clickable Sources on each company tab.
A13: Net AI economics (Totals + company tabs): Net AI = AI revenue - AI capex (full AI-infra) - AI opex (cash basis). With our arch: Net AI + spend cut.
A14: Shows they all LOSE money on AI today. TOGGLE 'Datacenter scaling factor' (Inputs B13): 0 = accelerator-only (conservative); 1 = whole datacenter scales -> net AI flips positive (~0.7 = breakeven).
... A44: Hyperscalers losing money on AI (capex vs revenue): https://fortune.com/2026/04/15/data-centers-hyperscalers-spending-billions-on-hardware-thats-worthless-in-3-years/
